Assignment3/Question1.v
// Q1: Design a datapath with three 8 bit accumulators. The first accumulator, acc1, adds a 4 bit input data in acc1 in every clock cycle. The second accumulator, acc2, adds the first accumulator in itself, and the third accumulator, acc3, adds the first and second accumulators in itself in every clock cycle. Each accumulator has an asynchronous reset. Draw the RTL level diagram and code the design in RTL Verilog.

module Question1(data,
                 clk,
                 reset,
                 out);
    input [3:0]data;
    input clk, reset;
    output [7:0]out;
    wire sum1, sum2;
    reg [7:0]acc1, acc2, acc3;
    
    assign sum1 = data + acc1;
    assign sum2 = sum1 + acc2;
    assign out  = sum1 + sum2 + acc3;
    always@(posedge clk, negedge reset)
    begin
        if (reset == 0)
        begin
            acc1 <= 0;
            acc2 <= 0;
            acc3 <= 0;
        end
        else
        begin
            acc1 <= sum1;
            acc2 <= sum2;
            acc3 <= out;
        end
    end
    
endmodule

Assignment3/Question1_tb.v
`include "Question1.v"

module Question1_tb();
    reg [3:0]data;
    reg clk, reset;
    wire [7:0]out;
    
    Question1 obj(data, clk, reset, out);
    initial
    begin
        $dumpfile("Question1.vcd");
        $dumpvars(0, Question1_tb);
        $display("done testing case %d", out);
        data = 0; reset = 0; clk = 0;
        #10
        data = 0; reset = 1;
        #10
        data = 1;
        #10
        data = 2;
        #10
        data = 3;
        #10
        $finish;
    end
    
    always // to generate clock
    begin
    #5
    clk = !clk;
    end
endmodule

Assignment3/Question1.vcd
$date
	Thu Oct 31 23:29:32 2019
$end
$version
	Icarus Verilog
$end
$timescale
	1s
$end
$scope module Question1_tb $end
$var wire 8 ! out [7:0] $end
$var reg 1 " clk $end
$var reg 4 # data [3:0] $end
$var reg 1 $ reset $end
$scope module obj $end
$var wire 1 " clk $end
$var wire 4 % data [3:0] $end
$var wire 1 $ reset $end
$var wire 1 & sum2 $end
$var wire 1 ' sum1 $end
$var wire 8 ( out [7:0] $end
$var reg 8 ) acc1 [7:0] $end
$var reg 8 * acc2 [7:0] $end
$var reg 8 + acc3 [7:0] $end
$upscope $end
$upscope $end
$enddefinitions $end
#0
$dumpvars
b0 +
b0 *
b0 )
b0 (
0'
0&
b0 %
0$
b0 #
0"
b0 !
$end
#5
1"
#10
0"
1$
#15
1"
#20
1&
b10 !
b10 (
1'
0"
b1 #
b1 %
#25
0'
b11 !
b11 (
b10 +
b1 *
b1 )
1"
#30
0&
b11 !
b11 (
1'
0"
b10 #
b10 %
#35
1&
b101 !
b101 (
b11 +
b0 *
1"
#40
0&
b11 !
b11 (
0'
0"
b11 #
b11 %
#45
1&
b101 !
b101 (
1'
b0 )
1"
