Assignment3/Question2.v
// Q2: Exercise question 2.10. Provide an RTL diagram and its relevant code; also test your code using a stimulus. Keep the input and output bit size equal to 4 bits.
// y[n] = x[n] - x[n-1] + x[n-2] + x[n-3] + 0.5y[n-1] + 0.25y[n-2]

module Question2(x,
                 clk,
                 reset,
                 y);
    input [3:0]x;
    input clk, reset;
    output [3:0]y;
    reg x1, x2, x3, y1, y2;
    
    assign y = x - x1 + x2 + x3 + (y1 >> 1) + (y2 >> 2);
    always@(posedge clk, negedge reset)
        if (reset == 0)
        begin
            x1 <= 0; x2 <= 0; x3 <= 0; y1 <= 0; y2 <= 0;
        end
        else
        begin
            x1 <= x;
            x2 <= x1;
            x3 <= x2;
            y1 <= y;
            y2 <= y1;
        end
endmodule

Assignment3/Question2_tb.v
`include "Question2.v"

module Question2_tb();
    reg [3:0]x;
    reg clk, reset;
    wire [3:0]y;
    
    Question2 obj(x, clk, reset, y);
    
    initial
    begin
        $dumpfile("Question2.vcd");
        $dumpvars(0, Question2_tb);
        $display("done testing case %d", y);
        x = 0; reset = 0; clk = 0;
        #10
        x = 0; reset = 1;
        #10
        x = 1;
        #10
        x = 2;
        #10
        x = 3;
        #10
        $finish;
    end
    
    always // to generate clock
    begin
    #5
    clk = !clk;
    end
endmodule

Assignment3/Question2.vcd
$date
	Fri Nov  1 00:05:23 2019
$end
$version
	Icarus Verilog
$end
$timescale
	1s
$end
$scope module Question2_tb $end
$var wire 4 ! y [3:0] $end
$var reg 1 " clk $end
$var reg 1 # reset $end
$var reg 4 $ x [3:0] $end
$scope module obj $end
$var wire 1 " clk $end
$var wire 1 # reset $end
$var wire 4 % x [3:0] $end
$var wire 4 & y [3:0] $end
$var reg 1 ' x1 $end
$var reg 1 ( x2 $end
$var reg 1 ) x3 $end
$var reg 1 * y1 $end
$var reg 1 + y2 $end
$upscope $end
$upscope $end
$enddefinitions $end
#0
$dumpvars
0+
0*
0)
0(
0'
b0 &
b0 %
b0 $
0#
0"
b0 !
$end
#5
1"
#10
0"
1#
#15
1"
#20
0"
b1 !
b1 &
b1 $
b1 %
#25
1*
b0 !
b0 &
1'
1"
#30
0"
b1 !
b1 &
b10 $
b10 %
#35
1+
1(
b11 !
b11 &
0'
1"
#40
0"
b100 !
b100 &
b11 $
b11 %
#45
0*
1)
0(
b11 !
b11 &
1'
1"
