Assignment3/Question3.v
// Q3: Complete the waveform for the given logic

module my_unit(clk,
               x,
               y1,
               y2);
    input clk, x;
    output y1, y2;
    reg y1, y2;
    wire w;
    
    assign w = x|(~y1);
    always@(posedge clk)
    begin
        y2 <= w;
    end
    
    always@(negedge clk)
    begin
        y1 <= y2;
    end
endmodule

Assignment3/Question3_tb.v
`include "Question3.v"

module Question3_tb();
    reg clk, x;
    wire y1, y2;
    
    my_unit obj(clk, x, y1, y2);
    
    initial
    begin
        $dumpfile("Question3.vcd");
        $dumpvars(0, Question3_tb);
        $display("done testing case %d", y1);
        clk = 0; x = 0;
        #10
        clk = 1;
        #10
        clk = 0;
        #10
        clk = 1; x = 1;
        #10
        clk = 0;
        #10
        clk = 1;
        #10
        clk = 0;
        #10
        clk = 1; x = 0;
        #10
        clk = 0;
        #10
        clk = 1; x = 1;
        #10
        clk = 0;
        #10
        clk = 1; x = 0;
        #10
        clk = 0;
        #10
        $finish;
    end
endmodule

Assignment3/Question3.vcd
$date
	Fri Nov  1 10:57:54 2019
$end
$version
	Icarus Verilog
$end
$timescale
	1s
$end
$scope module Question3_tb $end
$var wire 1 ! y2 $end
$var wire 1 " y1 $end
$var reg 1 # clk $end
$var reg 1 $ x $end
$scope module obj $end
$var wire 1 # clk $end
$var wire 1 % w $end
$var wire 1 $ x $end
$var reg 1 " y1 $end
$var reg 1 ! y2 $end
$upscope $end
$upscope $end
$enddefinitions $end
#0
$dumpvars
x%
0$
0#
x"
x!
$end
#10
1#
#20
0#
#30
1%
1$
1#
#40
0#
#50
1!
1#
#60
1"
0#
#70
0%
0$
1#
#80
0#
#90
0!
1%
1$
1#
#100
0"
0#
#110
1!
0$
1#
#120
0%
1"
0#
