Semester Project/mux2x1.v
module mux_2_1(a,
               b,
               s,
               out);
    input[7:0] a,b;
    input s;
    output[7:0] out;
    reg[7:0] out;
    
    always@ (*)
    begin
        if (s == 0)
        begin
            out <= a;
        end
        else
        begin
            out <= b;
        end
    end
endmodule

Semester Project/sobel.v
`include "mux2x1.v"
module sobel(clk,
             reset);
    // https://timetoexplore.net/blog/initialize-memory-in-verilog
    reg [7:0] ROM_IN  [0:4095];  // = > 64*64 - 1 = > sizeofimage - 1
    reg [7:0] ROM_OUT [0:4095];
    input clk, reset;
    reg [6:0] row, col, n;
    reg [3:0] count;
    reg [12:0] k,l0,l1,l2,l3,l4,l5,l6,l7,l8;
    
    initial
    begin
        n = 64;
        t = 27;
        // reading from in.txt and saving in ROM_IN from address 0 to 4095
        $readmemb ("in.txt", ROM_IN, 0, 4095);
        // $monitor("data_file handle was %0b", ROM_IN[38]);
        // writing to out.txt from ROM_IN from address 0 to 4095
        // $writememb("out.txt",ROM_OUT);
    end
    
    
    always@(posedge clk, negedge reset)
    begin
        if (reset == 0)
        begin
            row   = 1;
            col   = 1;
            count = 0;
        end
        else
        begin
            count = count + 1;
            if (count > 9)
            begin
                count = 0;
                col   = col+1;
                if (col > 64-2)
                begin
                    col = 1;
                    row = row + 1;
                    if (row > 64-2)
                    begin
                        row = 1;
                        $writememb("out.txt",ROM_OUT);
                        $finish();
                    end
                end
            end
        end
    end
    
    always@(row, col)
    begin
        k  = 0 + (row * n);
        l0 = k - n + col - 1;
        l1 = k - n + col;
        l2 = k - n + (col + 1);
        l3 = k + (col - 1);
        l4 = k + col;
        l5 = k + (col + 1);
        l6 = k + n + (col - 1);
        l7 = k + n + col;
        l8 = k + n + (col + 1);
    end
    
    
    reg [7:0] t;
    reg [7:0]s0,s1,s2,s3,s4,s5,s6,s7,s8;
    wire d;
    wire [7:0]a0,a1,a2,a3;
    wire [7:0]f9,f10,f11,f12,f13,f14;
    wire [7:0]g1,g2,g3,g4;
    wire c2,c5,c3,c4;
    wire [7:0]tem1,tem2;
    
    
    always@(posedge clk)
    begin
        if (count == 1)
            s0 <= ROM_IN[l0]>>2;
        else if (count == 2)
            s1 <= ROM_IN[l1]>>2;
        else if (count == 3)
            s2 <= ROM_IN[l2]>>2;
        else if (count == 4)
            s3 <= ROM_IN[l3]>>2;
        else if (count == 5)
            s4 <= ROM_IN[l4]>>2;
        else if (count == 6)
            s5 <= ROM_IN[l5]>>2;
        else if (count == 7)
            s6 <= ROM_IN[l6]>>2;
        else if (count == 8)
            s7 <= ROM_IN[l7]>>2;
        else if (count == 9)
        begin
            s8 <= ROM_IN[l8]>>2;
        end
        else
        begin
            // REMOVE THE ELSE BLOCK
        end
    end
    
    assign    a1 = s0+s1;
    assign    a3 = s1+s2;
    assign    a2 = s3+s6;
    assign   a0  = s5+s7;
    assign   f10 = a1+s3;
    assign   f11 = a3+s5;
    assign   f12 = a2+s7;
    assign   f9  = a0+s8;
    
    assign  g1         = f10-f9;
    assign  g3         = f11-f12;
    assign  {c2, g2}   = f11-f12;
    assign  {c5, g4}   = f10-f9;
    assign  {c3, tem1} = f14-t;
    assign  {c4, tem2} = f13-t;
    
    mux_2_1 ob1(g2,g3,c2,f14);
    mux_2_1 ob2(g4,g1,c5,f13);
    
    assign d = ~(c3&c4);
    always@(posedge clk)
        ROM_OUT[l4] = d;
    
endmodule
    
    // In order to read and write a file following commands are used in Verilog.
    // •	Reading a file in Verilog
    // reg [<memory_width>] <reg_name> [<memory_depth>];
    
    // initial
    // $readmemb ("<file_name>", <reg_name>, <start_address>, <end_address>);
    
    // •	Writing a file in verilog
    // always@(posedge	 clk)
    // $fwrite(<file_desc>, "%d", out);
    // initial
    // File_desc = $fopen(“filename.txt”,w);
    
    // integer id;
    // initial
    // Id = $fopen(“File path and name”, mode);	//here mode = “w”
    
    // always@(posedge clk)
    // begin
    //for reading sample by sample data and writing data into file
    // for file writing using following syntax
    // $fwrite(id, out);
    // $fwrite(id, “\n”); 	//for newline
    // end
    
    
    // ________________
    // | P0 | P1 | P2 |     --------> n columns
    // |----|----|----|     |
    // | P3 | P4 | P5 |     |
    // |----|----|----|     |
    // | P6 | P7 | P8 |     m rows
    // ----------------
    
    // | P0 |
    // | P1 |
    // | P2 |
    // | P3 |
    // | P4 |
    // | P5 |
    // | P6 |
    // | P7 |
    // | P8 |
    // row major
    
    // Variable ‘i’ represents row number whereas j represents column number
    // Variable ‘B’ is the base address of the array
    // Variable ‘n’ is the total number of the column of an image
    
    // get_Index obj(clk,row,j,l0,l1,l2,l3,l4,l5,l6,l7,l8);

Semester Project/sobel_tb.v
`timescale 1ns / 1ps
`include "sobel.v"

module sobel_tb();
    reg clk, reset;
    
    sobel obj(clk, reset);
    
    initial
    begin
        $dumpfile("sobel.vcd");
        $dumpvars(0, sobel_tb);
        reset = 1;
        #1
        reset = 0;
        clk   = 0;
        #1
        reset = 1;
    end
    
    
    always // to generate clock
    begin
    #10
    clk = !clk;
    end
    
endmodule

Semester Project/sobel.vcd
$date
	Wed Jan  8 03:09:40 2020
$end
$version
	Icarus Verilog
$end
$timescale
	1ps
$end
$scope module sobel_tb $end
$var reg 1 ! clk $end
$var reg 1 " reset $end
$scope module obj $end
$var wire 1 ! clk $end
$var wire 1 # d $end
$var wire 1 " reset $end
$var wire 8 $ tem2 [7:0] $end
$var wire 8 % tem1 [7:0] $end
$var wire 8 & g4 [7:0] $end
$var wire 8 ' g3 [7:0] $end
$var wire 8 ( g2 [7:0] $end
$var wire 8 ) g1 [7:0] $end
$var wire 8 * f9 [7:0] $end
$var wire 8 + f14 [7:0] $end
$var wire 8 , f13 [7:0] $end
$var wire 8 - f12 [7:0] $end
$var wire 8 . f11 [7:0] $end
$var wire 8 / f10 [7:0] $end
$var wire 1 0 c5 $end
$var wire 1 1 c4 $end
$var wire 1 2 c3 $end
$var wire 1 3 c2 $end
$var wire 8 4 a3 [7:0] $end
$var wire 8 5 a2 [7:0] $end
$var wire 8 6 a1 [7:0] $end
$var wire 8 7 a0 [7:0] $end
$var reg 7 8 col [6:0] $end
$var reg 4 9 count [3:0] $end
$var reg 13 : k [12:0] $end
$var reg 13 ; l0 [12:0] $end
$var reg 13 < l1 [12:0] $end
$var reg 13 = l2 [12:0] $end
$var reg 13 > l3 [12:0] $end
$var reg 13 ? l4 [12:0] $end
$var reg 13 @ l5 [12:0] $end
$var reg 13 A l6 [12:0] $end
$var reg 13 B l7 [12:0] $end
$var reg 13 C l8 [12:0] $end
$var reg 7 D n [6:0] $end
$var reg 7 E row [6:0] $end
$var reg 8 F s0 [7:0] $end
$var reg 8 G s1 [7:0] $end
$var reg 8 H s2 [7:0] $end
$var reg 8 I s3 [7:0] $end
$var reg 8 J s4 [7:0] $end
$var reg 8 K s5 [7:0] $end
$var reg 8 L s6 [7:0] $end
$var reg 8 M s7 [7:0] $end
$var reg 8 N s8 [7:0] $end
$var reg 8 O t [7:0] $end
$scope module ob1 $end
$var wire 8 P a [7:0] $end
$var wire 8 Q b [7:0] $end
$var wire 1 3 s $end
$var reg 8 R out [7:0] $end
$upscope $end
$scope module ob2 $end
$var wire 8 S a [7:0] $end
$var wire 8 T b [7:0] $end
$var wire 1 0 s $end
$var reg 8 U out [7:0] $end
$upscope $end
$upscope $end
$upscope $end
$enddefinitions $end
#0
$dumpvars
bx U
bx T
bx S
bx R
bx Q
bx P
b11011 O
bx N
bx M
bx L
bx K
bx J
bx I
bx H
bx G
bx F
bx E
b1000000 D
bx C
bx B
bx A
bx @
bx ?
bx >
bx =
bx <
bx ;
bx :
bx 9
bx 8
bx 7
bx 6
bx 5
bx 4
x3
x2
x1
x0
bx /
bx .
bx -
bx ,
bx +
bx *
bx )
bx (
bx '
bx &
bx %
bx $
x#
1"
x!
$end
#1000
b10000010 C
b10000001 B
b10000000 A
b1000010 @
b1000001 ?
b1000000 >
b10 =
b1 <
b0 ;
b1000000 :
b0 9
b1 8
b1 E
0!
0"
#2000
1"
#10000
b0 F
b1 9
1!
#20000
0!
#30000
b0 6
b0 G
b10 9
1!
#40000
0!
#50000
b0 4
b0 H
b11 9
1!
#60000
0!
#70000
b0 /
b0 I
b100 9
1!
#80000
0!
#90000
b0 J
b101 9
1!
#100000
0!
#110000
b0 .
b0 K
b110 9
1!
#120000
0!
#130000
b0 5
b0 L
b111 9
1!
#140000
0!
#150000
b11100101 %
12
b0 +
b0 R
b0 (
b0 P
03
b0 7
b0 '
b0 Q
b0 -
b0 M
b1000 9
1!
#160000
0!
#170000
0#
b11100101 $
11
b0 ,
b0 U
b0 &
b0 S
00
b0 )
b0 T
b0 *
b0 N
b1001 9
1!
#180000
0!
#190000
b10000011 C
b10000010 B
b10000001 A
b1000011 @
b1000010 ?
b1000001 >
b11 =
b10 <
b1 ;
b10 8
b0 9
1!
#200000
0!
#210000
b1 9
1!
#220000
0!
#230000
b10 9
1!
#240000
0!
#250000
b11 9
1!
#260000
0!
#270000
b100 9
1!
#280000
0!
#290000
b101 9
1!
#300000
0!
#310000
b110 9
1!
#320000
0!
#330000
b111 9
1!
#340000
0!
#350000
b1000 9
1!
#360000
0!
#370000
b1001 9
1!
#380000
0!
#390000
b10000100 C
b10000011 B
b10000010 A
b1000100 @
b1000011 ?
b1000010 >
b100 =
b11 <
b10 ;
b11 8
b0 9
1!
#400000
0!
#410000
b1 9
1!
#420000
0!
#430000
b10 9
1!
#440000
0!
#450000
b11 9
1!
#460000
0!
#470000
b100 9
1!
#480000
0!
#490000
b101 9
1!
#500000
0!
#510000
b110 9
1!
#520000
0!
#530000
b111 9
1!
#540000
0!
#550000
b1000 9
1!
#560000
0!
#570000
b1001 9
1!
#580000
0!
#590000
b10000101 C
b10000100 B
b10000011 A
b1000101 @
b1000100 ?
b1000011 >
b101 =
b100 <
b11 ;
b100 8
b0 9
1!
#600000
0!
#610000
b1 9
1!
#620000
0!
#630000
b10 9
1!
#640000
0!
#650000
b11 9
1!
#660000
0!
#670000
b100 9
1!
#680000
0!
#690000
b101 9
1!
#700000
0!
#710000
b110 9
1!
#720000
0!
#730000
b111 9
1!
#740000
0!
#750000
b1000 9
1!
#760000
0!
#770000
b1001 9
1!
#780000
0!
#790000
b10000110 C
b10000101 B
b10000100 A
b1000110 @
b1000101 ?
b1000100 >
b110 =
b101 <
b100 ;
b101 8
b0 9
1!
#800000
0!
#810000
b1 9
1!
#820000
0!
#830000
b10 9
1!
#840000
0!
#850000
b11 9
1!
#860000
0!
#870000
b100 9
1!
#880000
0!
#890000
b101 9
1!
#900000
0!
#910000
b110 9
1!
#920000
0!
#930000
b111 9
1!
#940000
0!
#950000
b1000 9
1!
#960000
0!
#970000
b1001 9
1!
#980000
0!
#990000
b10000111 C
b10000110 B
b10000101 A
b1000111 @
b1000110 ?
b1000101 >
b111 =
b110 <
b101 ;
b110 8
b0 9
1!
#1000000
0!
#1010000
b1 9
1!
#1020000
0!
#1030000
b10 9
1!
#1040000
0!
#1050000
b11 9
1!
#1060000
0!
#1070000
b100 9
1!
#1080000
0!
#1090000
b101 9
1!
#1100000
0!
#1110000
b110 9
1!
#1120000
0!
#1130000
b111 9
1!
#1140000
0!
#1150000
b1000 9
1!
#1160000
0!
#1170000
b1001 9
1!
#1180000
0!
#1190000
b10001000 C
b10000111 B
b10000110 A
b1001000 @
b1000111 ?
b1000110 >
b1000 =
b111 <
b110 ;
b111 8
b0 9
1!
#1200000
0!
#1210000
b1 9
1!
#1220000
0!
#1230000
b10 9
1!
#1240000
0!
#1250000
b11 9
1!
#1260000
0!
#1270000
b100 9
1!
#1280000
0!
#1290000
b101 9
1!
#1300000
0!
#1310000
b110 9
1!
#1320000
0!
#1330000
b111 9
1!
#1340000
0!
#1350000
b1000 9
1!
#1360000
0!
#1370000
b1001 9
1!
#1380000
0!
#1390000
b10001001 C
b10001000 B
b10000111 A
b1001001 @
b1001000 ?
b1000111 >
b1001 =
b1000 <
b111 ;
b1000 8
b0 9
1!
#1400000
0!
#1410000
b1 9
1!
#1420000
0!
#1430000
b10 9
1!
#1440000
0!
#1450000
b11 9
1!
#1460000
0!
#1470000
b100 9
1!
#1480000
0!
#1490000
b101 9
1!
#1500000
0!
#1510000
b110 9
1!
#1520000
0!
#1530000
b111 9
1!
#1540000
0!
#1550000
b1000 9
1!
#1560000
0!
#1570000
b1001 9
1!
#1580000
0!
#1590000
b10001010 C
b10001001 B
b10001000 A
b1001010 @
b1001001 ?
b1001000 >
b1010 =
b1001 <
b1000 ;
b1001 8
b0 9
1!
#1600000
0!
#1610000
b1 9
1!
#1620000
0!
#1630000
b10 9
1!
#1640000
0!
#1650000
b11 9
1!
#1660000
0!
#1670000
b100 9
1!
#1680000
0!
#1690000
b101 9
1!
#1700000
0!
#1710000
b110 9
1!
#1720000
0!
#1730000
b111 9
1!
#1740000
0!
#1750000
b1000 9
1!
#1760000
0!
#1770000
b1001 9
1!
#1780000
0!
#1790000
b10001011 C
b10001010 B
b10001001 A
b1001011 @
b1001010 ?
b1001001 >
b1011 =
b1010 <
b1001 ;
b1010 8
b0 9
1!
#1800000
0!
#1810000
b1 9
1!
#1820000
0!
#1830000
b10 9
1!
#1840000
0!
#1850000
b11 9
1!
#1860000
0!
#1870000
b100 9
1!
#1880000
0!
#1890000
b101 9
1!
#1900000
0!
#1910000
b110 9
1!
#1920000
0!
#1930000
b111 9
1!
#1940000
0!
#1950000
b1000 9
1!
#1960000
0!
#1970000
b1001 9
1!
#1980000
0!
#1990000
b10001100 C
b10001011 B
b10001010 A
b1001100 @
b1001011 ?
b1001010 >
b1100 =
b1011 <
b1010 ;
b1011 8
b0 9
1!
#2000000
0!
#2010000
b1 9
1!
#2020000
0!
#2030000
b10 9
1!
#2040000
0!
#2050000
b11 9
1!
#2060000
0!
#2070000
b100 9
1!
#2080000
0!
#2090000
b101 9
1!
#2100000
0!
#2110000
b110 9
1!
#2120000
0!
#2130000
b111 9
1!
#2140000
0!
#2150000
b1000 9
1!
#2160000
0!
#2170000
b1001 9
1!
#2180000
0!
#2190000
b10001101 C
b10001100 B
b10001011 A
b1001101 @
b1001100 ?
b1001011 >
b1101 =
b1100 <
b1011 ;
b1100 8
b0 9
1!
#2200000
0!
#2210000
b1 9
1!
#2220000
0!
#2230000
b10 9
1!
#2240000
0!
#2250000
b11 9
1!
#2260000
0!
#2270000
b100 9
1!
#2280000
0!
#2290000
b101 9
1!
#2300000
0!
#2310000
b110 9
1!
#2320000
0!
#2330000
b111 9
1!
#2340000
0!
#2350000
b1000 9
1!
#2360000
0!
#2370000
b1001 9
1!
#2380000
0!
#2390000
b10001110 C
b10001101 B
b10001100 A
b1001110 @
b1001101 ?
b1001100 >
b1110 =
b1101 <
b1100 ;
b1101 8
b0 9
1!
#2400000
0!
#2410000
b1 9
1!
#2420000
0!
#2430000
b10 9
1!
#2440000
0!
#2450000
b11 9
1!
#2460000
0!
#2470000
b100 9
1!
#2480000
0!
#2490000
b101 9
1!
#2500000
0!
#2510000
b110 9
1!
#2520000
0!
#2530000
b111 9
1!
#2540000
0!
#2550000
b1000 9
1!
#2560000
0!
#2570000
b1001 9
1!
#2580000
0!
#2590000
b10001111 C
b10001110 B
b10001101 A
b1001111 @
b1001110 ?
b1001101 >
b1111 =
b1110 <
b1101 ;
b1110 8
b0 9
1!
#2600000
0!
#2610000
b1 9
1!
#2620000
0!
#2630000
b10 9
1!
#2640000
0!
#2650000
b11 9
1!
#2660000
0!
#2670000
b100 9
1!
#2680000
0!
#2690000
b101 9
1!
#2700000
0!
#2710000
b110 9
1!
#2720000
0!
#2730000
b111 9
1!
#2740000
0!
#2750000
b1000 9
1!
#2760000
0!
#2770000
b1001 9
1!
#2780000
0!
#2790000
b10010000 C
b10001111 B
b10001110 A
b1010000 @
b1001111 ?
b1001110 >
b10000 =
b1111 <
b1110 ;
b1111 8
b0 9
1!
#2800000
0!
#2810000
b1 9
1!
#2820000
0!
#2830000
b10 9
1!
#2840000
0!
#2850000
b11 9
1!
#2860000
0!
#2870000
b100 9
1!
#2880000
0!
#2890000
b101 9
1!
#2900000
0!
#2910000
b110 9
1!
#2920000
0!
#2930000
b111 9
1!
#2940000
0!
#2950000
b1000 9
1!
#2960000
0!
#2970000
b1001 9
1!
#2980000
0!
#2990000
b10010001 C
b10010000 B
b10001111 A
b1010001 @
b1010000 ?
b1001111 >
b10001 =
b10000 <
b1111 ;
b10000 8
b0 9
1!
#3000000
0!
#3010000
b1 9
1!
#3020000
0!
#3030000
b10 9
1!
#3040000
0!
#3050000
b11 9
1!
#3060000
0!
#3070000
b100 9
1!
#3080000
0!
#3090000
b101 9
1!
#3100000
0!
#3110000
b110 9
1!
#3120000
0!
#3130000
b111 9
1!
#3140000
0!
#3150000
b1000 9
1!
#3160000
0!
#3170000
b1001 9
1!
#3180000
0!
#3190000
b10010010 C
b10010001 B
b10010000 A
b1010010 @
b1010001 ?
b1010000 >
b10010 =
b10001 <
b10000 ;
b10001 8
b0 9
1!
#3200000
0!
#3210000
b1 9
1!
#3220000
0!
#3230000
b10 9
1!
#3240000
0!
#3250000
b11 9
1!
#3260000
0!
#3270000
b100 9
1!
#3280000
0!
#3290000
b101 9
1!
#3300000
0!
#3310000
b110 9
1!
#3320000
0!
#3330000
b111 9
1!
#3340000
0!
#3350000
b1000 9
1!
#3360000
0!
#3370000
1#
b10100110 $
01
b11000001 ,
b11000001 U
b11000001 &
b11000001 S
10
b11000001 )
b11000001 T
b111111 *
b111111 N
b1001 9
1!
#3380000
0!
#3390000
b10010011 C
b10010010 B
b10010001 A
b1010011 @
b1010010 ?
b1010001 >
b10011 =
b10010 <
b10001 ;
b10010 8
b0 9
1!
#3400000
0!
#3410000
b1 9
1!
#3420000
0!
#3430000
b10 9
1!
#3440000
0!
#3450000
b11 9
1!
#3460000
0!
#3470000
b100 9
1!
#3480000
0!
#3490000
b101 9
1!
#3500000
0!
#3510000
b110 9
1!
#3520000
0!
#3530000
b111 9
1!
#3540000
0!
#3550000
b1100111 $
b10100110 %
02
b10000010 ,
b10000010 U
b11000001 +
b11000001 R
b10000010 &
b10000010 S
b11000001 (
b11000001 P
13
b10000010 )
b10000010 T
b1111110 *
b111111 7
b11000001 '
b11000001 Q
b111111 -
b111111 M
b1000 9
1!
#3560000
0!
#3570000
b1001 9
1!
#3580000
0!
#3590000
b10010100 C
b10010011 B
b10010010 A
b1010100 @
b1010011 ?
b1010010 >
b10100 =
b10011 <
b10010 ;
b10011 8
b0 9
1!
#3600000
0!
#3610000
b1 9
1!
#3620000
0!
#3630000
b10 9
1!
#3640000
0!
#3650000
b11 9
1!
#3660000
0!
#3670000
b100 9
1!
#3680000
0!
#3690000
b101 9
1!
#3700000
0!
#3710000
b101000 $
b11100101 %
12
b1000011 ,
b1000011 U
b0 +
b0 R
b1000011 &
b1000011 S
b0 (
b0 P
03
b1000011 )
b1000011 T
b10111101 *
b1111110 7
b0 '
b0 Q
b111111 .
b111111 K
b110 9
1!
#3720000
0!
#3730000
b10100110 %
02
b11000001 +
b11000001 R
b11000001 (
b11000001 P
13
b11000001 '
b11000001 Q
b1111110 -
b111111 5
b111111 L
b111 9
1!
#3740000
0!
#3750000
b1000 9
1!
#3760000
0!
#3770000
b1001 9
1!
#3780000
0!
#3790000
b10010101 C
b10010100 B
b10010011 A
b1010101 @
b1010100 ?
b1010011 >
b10101 =
b10100 <
b10011 ;
b10100 8
b0 9
1!
#3800000
0!
#3810000
b1 9
1!
#3820000
0!
#3830000
b10 9
1!
#3840000
0!
#3850000
b11 9
1!
#3860000
0!
#3870000
b100 9
1!
#3880000
0!
#3890000
b111111 J
b101 9
1!
#3900000
0!
#3910000
b110 9
1!
#3920000
0!
#3930000
b111 9
1!
#3940000
0!
#3950000
b1000 9
1!
#3960000
0!
#3970000
b1001 9
1!
#3980000
0!
#3990000
b10010110 C
b10010101 B
b10010100 A
b1010110 @
b1010101 ?
b1010100 >
b10110 =
b10101 <
b10100 ;
b10101 8
b0 9
1!
#4000000
0!
#4010000
b1 9
1!
#4020000
0!
#4030000
b10 9
1!
#4040000
0!
#4050000
b11 9
1!
#4060000
0!
#4070000
b1100111 %
b1100111 $
b10000010 +
b10000010 R
b10000010 ,
b10000010 U
b10000010 (
b10000010 P
b10000010 &
b10000010 S
b10000010 '
b10000010 Q
b10111101 -
b1111110 5
b10000010 )
b10000010 T
b111111 /
b111111 I
b100 9
1!
#4080000
0!
#4090000
b101 9
1!
#4100000
0!
#4110000
b110 9
1!
#4120000
0!
#4130000
b111 9
1!
#4140000
0!
#4150000
b1000 9
1!
#4160000
0!
#4170000
b1001 9
1!
#4180000
0!
#4190000
b10010111 C
b10010110 B
b10010101 A
b1010111 @
b1010110 ?
b1010101 >
b10111 =
b10110 <
b10101 ;
b10110 8
b0 9
1!
#4200000
0!
#4210000
b1 9
1!
#4220000
0!
#4230000
b10 9
1!
#4240000
0!
#4250000
b11 9
1!
#4260000
0!
#4270000
b100 9
1!
#4280000
0!
#4290000
b101 9
1!
#4300000
0!
#4310000
b110 9
1!
#4320000
0!
#4330000
b111 9
1!
#4340000
0!
#4350000
b1000 9
1!
#4360000
0!
#4370000
b1001 9
1!
#4380000
0!
#4390000
b10011000 C
b10010111 B
b10010110 A
b1011000 @
b1010111 ?
b1010110 >
b11000 =
b10111 <
b10110 ;
b10111 8
b0 9
1!
#4400000
0!
#4410000
b1 9
1!
#4420000
0!
#4430000
b10 9
1!
#4440000
0!
#4450000
b10100110 %
b11000001 +
b11000001 R
b11000001 (
b11000001 P
b11000001 '
b11000001 Q
b1111110 .
b111111 4
b111111 H
b11 9
1!
#4460000
0!
#4470000
b100 9
1!
#4480000
0!
#4490000
b101 9
1!
#4500000
0!
#4510000
b110 9
1!
#4520000
0!
#4530000
b111 9
1!
#4540000
0!
#4550000
b1000 9
1!
#4560000
0!
#4570000
b1001 9
1!
#4580000
0!
#4590000
b10011001 C
b10011000 B
b10010111 A
b1011001 @
b1011000 ?
b1010111 >
b11001 =
b11000 <
b10111 ;
b11000 8
b0 9
1!
#4600000
0!
#4610000
b1 9
1!
#4620000
0!
#4630000
b10100110 $
b11100101 %
12
b11000001 ,
b11000001 U
b0 +
b0 R
b11000001 &
b11000001 S
b0 (
b0 P
03
b11000001 )
b11000001 T
b1111110 /
b111111 6
b0 '
b0 Q
b10111101 .
b1111110 4
b111111 G
b10 9
1!
#4640000
0!
#4650000
b11 9
1!
#4660000
0!
#4670000
b100 9
1!
#4680000
0!
#4690000
b101 9
1!
#4700000
0!
#4710000
b110 9
1!
#4720000
0!
#4730000
b111 9
1!
#4740000
0!
#4750000
b1000 9
1!
#4760000
0!
#4770000
b1001 9
1!
#4780000
0!
#4790000
b10011010 C
b10011001 B
b10011000 A
b1011010 @
b1011001 ?
b1011000 >
b11010 =
b11001 <
b11000 ;
b11001 8
b0 9
1!
#4800000
0!
#4810000
0#
b11100101 $
11
b0 ,
b0 U
b0 &
b0 S
00
b0 )
b0 T
b10111101 /
b1111110 6
b111111 F
b1 9
1!
#4820000
0!
#4830000
b10 9
1!
#4840000
0!
#4850000
b11 9
1!
#4860000
0!
#4870000
b100 9
1!
#4880000
0!
#4890000
b101 9
1!
#4900000
0!
#4910000
b110 9
1!
#4920000
0!
#4930000
b111 9
1!
#4940000
0!
#4950000
b1000 9
1!
#4960000
0!
#4970000
b1001 9
1!
#4980000
0!
#4990000
b10011011 C
b10011010 B
b10011001 A
b1011011 @
b1011010 ?
b1011001 >
b11011 =
b11010 <
b11001 ;
b11010 8
b0 9
1!
#5000000
0!
#5010000
b1 9
1!
#5020000
0!
#5030000
b10 9
1!
#5040000
0!
#5050000
b11 9
1!
#5060000
0!
#5070000
b100 9
1!
#5080000
0!
#5090000
b101 9
1!
#5100000
0!
#5110000
b110 9
1!
#5120000
0!
#5130000
b111 9
1!
#5140000
0!
#5150000
b1000 9
1!
#5160000
0!
#5170000
b1001 9
1!
#5180000
0!
#5190000
b10011100 C
b10011011 B
b10011010 A
b1011100 @
b1011011 ?
b1011010 >
b11100 =
b11011 <
b11010 ;
b11011 8
b0 9
1!
#5200000
0!
#5210000
b1 9
1!
#5220000
0!
#5230000
b10 9
1!
#5240000
0!
#5250000
b11 9
1!
#5260000
0!
#5270000
b100 9
1!
#5280000
0!
#5290000
b101 9
1!
#5300000
0!
#5310000
b110 9
1!
#5320000
0!
#5330000
b111 9
1!
#5340000
0!
#5350000
b1000 9
1!
#5360000
0!
#5370000
b1001 9
1!
#5380000
0!
#5390000
b10011101 C
b10011100 B
b10011011 A
b1011101 @
b1011100 ?
b1011011 >
b11101 =
b11100 <
b11011 ;
b11100 8
b0 9
1!
#5400000
0!
#5410000
b1 9
1!
#5420000
0!
#5430000
b10 9
1!
#5440000
0!
#5450000
b11 9
1!
#5460000
0!
#5470000
b100 9
1!
#5480000
0!
#5490000
b101 9
1!
#5500000
0!
#5510000
b110 9
1!
#5520000
0!
#5530000
b111 9
1!
#5540000
0!
#5550000
b1000 9
1!
#5560000
0!
#5570000
b1001 9
1!
#5580000
0!
#5590000
b10011110 C
b10011101 B
b10011100 A
b1011110 @
b1011101 ?
b1011100 >
b11110 =
b11101 <
b11100 ;
b11101 8
b0 9
1!
#5600000
0!
#5610000
b1 9
1!
#5620000
0!
#5630000
b10 9
1!
#5640000
0!
#5650000
b11 9
1!
#5660000
0!
#5670000
b100 9
1!
#5680000
0!
#5690000
b101 9
1!
#5700000
0!
#5710000
b110 9
1!
#5720000
0!
#5730000
b111 9
1!
#5740000
0!
#5750000
b1000 9
1!
#5760000
0!
#5770000
b1001 9
1!
#5780000
0!
#5790000
b10011111 C
b10011110 B
b10011101 A
b1011111 @
b1011110 ?
b1011101 >
b11111 =
b11110 <
b11101 ;
b11110 8
b0 9
1!
#5800000
0!
#5810000
b1 9
1!
#5820000
0!
#5830000
b10 9
1!
#5840000
0!
#5850000
b11 9
1!
#5860000
0!
#5870000
b100 9
1!
#5880000
0!
#5890000
b101 9
1!
#5900000
0!
#5910000
b110 9
1!
#5920000
0!
#5930000
b111 9
1!
#5940000
0!
#5950000
b1000 9
1!
#5960000
0!
#5970000
b1001 9
1!
#5980000
0!
#5990000
b10100000 C
b10011111 B
b10011110 A
b1100000 @
b1011111 ?
b1011110 >
b100000 =
b11111 <
b11110 ;
b11111 8
b0 9
1!
#6000000
0!
#6010000
b1 9
1!
#6020000
0!
#6030000
b10 9
1!
#6040000
0!
#6050000
b11 9
1!
#6060000
0!
#6070000
b100 9
1!
#6080000
0!
#6090000
b101 9
1!
#6100000
0!
#6110000
b110 9
1!
#6120000
0!
#6130000
b111 9
1!
#6140000
0!
#6150000
b1000 9
1!
#6160000
0!
#6170000
b1001 9
1!
#6180000
0!
#6190000
b10100001 C
b10100000 B
b10011111 A
b1100001 @
b1100000 ?
b1011111 >
b100001 =
b100000 <
b11111 ;
b100000 8
b0 9
1!
#6200000
0!
#6210000
b1 9
1!
#6220000
0!
#6230000
b10 9
1!
#6240000
0!
#6250000
b11 9
1!
#6260000
0!
#6270000
b100 9
1!
#6280000
0!
#6290000
b101 9
1!
#6300000
0!
#6310000
b110 9
1!
#6320000
0!
#6330000
b111 9
1!
#6340000
0!
#6350000
b1000 9
1!
#6360000
0!
#6370000
b1001 9
1!
#6380000
0!
#6390000
b10100010 C
b10100001 B
b10100000 A
b1100010 @
b1100001 ?
b1100000 >
b100010 =
b100001 <
b100000 ;
b100001 8
b0 9
1!
#6400000
0!
#6410000
b1 9
1!
#6420000
0!
#6430000
b10 9
1!
#6440000
0!
#6450000
b11 9
1!
#6460000
0!
#6470000
b100 9
1!
#6480000
0!
#6490000
b101 9
1!
#6500000
0!
#6510000
b110 9
1!
#6520000
0!
#6530000
b111 9
1!
#6540000
0!
#6550000
b1000 9
1!
#6560000
0!
#6570000
b1001 9
1!
#6580000
0!
#6590000
b10100011 C
b10100010 B
b10100001 A
b1100011 @
b1100010 ?
b1100001 >
b100011 =
b100010 <
b100001 ;
b100010 8
b0 9
1!
#6600000
0!
#6610000
b1 9
1!
#6620000
0!
#6630000
b10 9
1!
#6640000
0!
#6650000
b11 9
1!
#6660000
0!
#6670000
b100 9
1!
#6680000
0!
#6690000
b101 9
1!
#6700000
0!
#6710000
b110 9
1!
#6720000
0!
#6730000
b111 9
1!
#6740000
0!
#6750000
b1000 9
1!
#6760000
0!
#6770000
b1001 9
1!
#6780000
0!
#6790000
b10100100 C
b10100011 B
b10100010 A
b1100100 @
b1100011 ?
b1100010 >
b100100 =
b100011 <
b100010 ;
b100011 8
b0 9
1!
#6800000
0!
#6810000
b1 9
1!
#6820000
0!
#6830000
b10 9
1!
#6840000
0!
#6850000
b11 9
1!
#6860000
0!
#6870000
b100 9
1!
#6880000
0!
#6890000
b101 9
1!
#6900000
0!
#6910000
b110 9
1!
#6920000
0!
#6930000
b111 9
1!
#6940000
0!
#6950000
b1000 9
1!
#6960000
0!
#6970000
b1001 9
1!
#6980000
0!
#6990000
b10100101 C
b10100100 B
b10100011 A
b1100101 @
b1100100 ?
b1100011 >
b100101 =
b100100 <
b100011 ;
b100100 8
b0 9
1!
#7000000
0!
#7010000
b1 9
1!
#7020000
0!
#7030000
b10 9
1!
#7040000
0!
#7050000
b11 9
1!
#7060000
0!
#7070000
b100 9
1!
#7080000
0!
#7090000
b101 9
1!
#7100000
0!
#7110000
b110 9
1!
#7120000
0!
#7130000
b111 9
1!
#7140000
0!
#7150000
b1000 9
1!
#7160000
0!
#7170000
b1001 9
1!
#7180000
0!
#7190000
b10100110 C
b10100101 B
b10100100 A
b1100110 @
b1100101 ?
b1100100 >
b100110 =
b100101 <
b100100 ;
b100101 8
b0 9
1!
#7200000
0!
#7210000
b1 9
1!
#7220000
0!
#7230000
b10 9
1!
#7240000
0!
#7250000
b11 9
1!
#7260000
0!
