Semester Project/sobel.v
`timescale 1ns / 1ps

module sobel(d);
    // https://timetoexplore.net/blog/initialize-memory-in-verilog
    reg [7:0] ROM_IN  [0:4095];  // = > 64*64 - 1 = > sizeofimage - 1
    reg [7:0] ROM_OUT [0:4095];
    reg clk, reset;
    reg [6:0] i, j, n;
    reg [3:0] count;
    reg [12:0] k,l0,l1,l2,l3,l4,l5,l6,l7,l8;
    
    initial
    begin
        $dumpfile("sobel.vcd");
        $dumpvars(0, sobel);
        reset = 1;
        #5
        reset = 0;
        clk   = 0;
        #5
        n     = 64;
        t     = 27;
        reset = 1;
        // reading from in.txt and saving in ROM_IN from address 0 to 4095
        $readmemb ("in.txt", ROM_IN, 0, 4095);
        // $monitor("data_file handle was %0b", ROM_IN[38]);
        // writing to out.txt from ROM_IN from address 0 to 4095
        // $writememb("out.txt",ROM_OUT);
        
    end
    
    always@(posedge clk, negedge reset)
    begin
        if (reset == 0 || count == 9)
        begin
            count <= 0;
        end
        else
        begin
            count <= count + 1;
        end
    end
    
    always@(posedge clk, negedge reset)
    begin
        if (reset == 0)
        begin
            i = 1;
            j = 0;
        end
        else
        begin
            // $monitor("count %d", count);
            if (count == 0)
            begin
                j = j+1;
                if (j > 64-2)
                begin
                    j = 1;
                    i = i + 1;
                    if (i > 64-2)
                    begin
                        i = 1;
                        $writememb("out.txt",ROM_OUT);
                        $finish();
                    end
                end
            end
        end
    end
    
    always@(i, j)
    begin
        k  = 0 + (i * n);
        l0 = k - n + j - 1;
        l1 = k - n + j;
        l2 = k - n + (j + 1);
        l3 = k + (j - 1);
        l4 = k + j;
        l5 = k + (j + 1);
        l6 = k + n + (j - 1);
        l7 = k + n + j;
        l8 = k + n + (j + 1);
    end
    
    always // to generate clock
    begin
    #10
    clk = !clk;
    end
    
    reg [7:0] t;
    reg [7:0]s0,s1,s2,s3,s4,s5,s6,s7,s8;
    output wire d;
    wire [7:0]a0,a1,a2,a3;
    wire [7:0]f9,f10,f11,f12,f13,f14;
    wire [7:0]g1,g2,g3,g4;
    wire c2,c5,c3,c4;
    wire [7:0]tem1,tem2;
    
    
    
    always@(posedge clk)
    begin
        if (count == 1)
            s0 <= ROM_IN[l0]>>2;
        else if (count == 2)
            s1 <= ROM_IN[l1]>>2;
        else if (count == 3)
            s2 <= ROM_IN[l2]>>2;
        else if (count == 4)
            s3 <= ROM_IN[l3]>>2;
        else if (count == 5)
            s4 <= ROM_IN[l4]>>2;
        else if (count == 6)
            s5 <= ROM_IN[l5]>>2;
        else if (count == 7)
            s6 <= ROM_IN[l6]>>2;
        else if (count == 8)
            s7 <= ROM_IN[l7]>>2;
        else if (count == 9)
        begin
            s8 <= ROM_IN[l8]>>2;
        end
        else
        begin
            
        end
    end
    
    assign    a1 = s0+s1;
    assign    a3 = s1+s2;
    assign    a2 = s3+s6;
    assign   a0  = s5+s7;
    assign   f10 = a1+s3;
    assign   f11 = a3+s5;
    assign   f12 = a2+s7;
    assign   f9  = a0+s8;
    
    assign  g1         = f10-f9;
    assign  g3         = f11-f12;
    assign  {c2, g2}   = f11-f12;
    assign  {c5, g4}   = f10-f9;
    assign  {c3, tem1} = f14-t;
    assign  {c4, tem2} = f13-t;
    
    mux_2_1 ob1(g2,g3,c2,f14);
    mux_2_1 ob2(g4,g1,c5,f13);
    
    assign d = ~(c3&c4);
    always@(posedge clk)
        ROM_OUT[l4] = d;
    
endmodule
    
    module mux_2_1(a,b,s,out);
        input[7:0] a,b;
        input s;
        output[7:0] out;
        reg[7:0] out;
        
        always@ (*)
        begin
            if (s == 0)
            begin
                out <= a;
            end
            else
            begin
                out <= b;
            end
        end
    endmodule
        
        // In order to read and write a file following commands are used in Verilog.
        // •	Reading a file in Verilog
        // reg [<memory_width>] <reg_name> [<memory_depth>];
        
        // initial
        // $readmemb ("<file_name>", <reg_name>, <start_address>, <end_address>);
        
        // •	Writing a file in verilog
        // always@(posedge	 clk)
        // $fwrite(<file_desc>, "%d", out);
        // initial
        // File_desc = $fopen(“filename.txt”,w);
        
        // integer id;
        // initial
        // Id = $fopen(“File path and name”, mode);	//here mode = “w”
        
        // always@(posedge clk)
        // begin
        //for reading sample by sample data and writing data into file
        // for file writing using following syntax
        // $fwrite(id, out);
        // $fwrite(id, “\n”); 	//for newline
        // end
        
        
        // ________________
        // | P0 | P1 | P2 |     --------> n columns
        // |----|----|----|     |
        // | P3 | P4 | P5 |     |
        // |----|----|----|     |
        // | P6 | P7 | P8 |     m rows
        // ----------------
        
        // | P0 |
        // | P1 |
        // | P2 |
        // | P3 |
        // | P4 |
        // | P5 |
        // | P6 |
        // | P7 |
        // | P8 |
        // row major
        
        // Variable ‘i’ represents row number whereas j represents column number
        // Variable ‘B’ is the base address of the array
        // Variable ‘n’ is the total number of the column of an image
        
        // get_Index obj(clk,i,j,l0,l1,l2,l3,l4,l5,l6,l7,l8);

Semester Project/sobel.vcd
$date
	Sun Jan  5 17:32:12 2020
$end
$version
	Icarus Verilog
$end
$timescale
	1ps
$end
$scope module sobel $end
$var wire 1 ! d $end
$var wire 8 " tem2 [7:0] $end
$var wire 8 # tem1 [7:0] $end
$var wire 8 $ g4 [7:0] $end
$var wire 8 % g3 [7:0] $end
$var wire 8 & g2 [7:0] $end
$var wire 8 ' g1 [7:0] $end
$var wire 8 ( f9 [7:0] $end
$var wire 8 ) f14 [7:0] $end
$var wire 8 * f13 [7:0] $end
$var wire 8 + f12 [7:0] $end
$var wire 8 , f11 [7:0] $end
$var wire 8 - f10 [7:0] $end
$var wire 1 . c5 $end
$var wire 1 / c4 $end
$var wire 1 0 c3 $end
$var wire 1 1 c2 $end
$var wire 8 2 a3 [7:0] $end
$var wire 8 3 a2 [7:0] $end
$var wire 8 4 a1 [7:0] $end
$var wire 8 5 a0 [7:0] $end
$var reg 1 6 clk $end
$var reg 4 7 count [3:0] $end
$var reg 7 8 i [6:0] $end
$var reg 7 9 j [6:0] $end
$var reg 13 : k [12:0] $end
$var reg 13 ; l0 [12:0] $end
$var reg 13 < l1 [12:0] $end
$var reg 13 = l2 [12:0] $end
$var reg 13 > l3 [12:0] $end
$var reg 13 ? l4 [12:0] $end
$var reg 13 @ l5 [12:0] $end
$var reg 13 A l6 [12:0] $end
$var reg 13 B l7 [12:0] $end
$var reg 13 C l8 [12:0] $end
$var reg 7 D n [6:0] $end
$var reg 1 E reset $end
$var reg 8 F s0 [7:0] $end
$var reg 8 G s1 [7:0] $end
$var reg 8 H s2 [7:0] $end
$var reg 8 I s3 [7:0] $end
$var reg 8 J s4 [7:0] $end
$var reg 8 K s5 [7:0] $end
$var reg 8 L s6 [7:0] $end
$var reg 8 M s7 [7:0] $end
$var reg 8 N s8 [7:0] $end
$var reg 8 O t [7:0] $end
$scope module ob1 $end
$var wire 8 P a [7:0] $end
$var wire 8 Q b [7:0] $end
$var wire 1 1 s $end
$var reg 8 R out [7:0] $end
$upscope $end
$scope module ob2 $end
$var wire 8 S a [7:0] $end
$var wire 8 T b [7:0] $end
$var wire 1 . s $end
$var reg 8 U out [7:0] $end
$upscope $end
$upscope $end
$enddefinitions $end
#0
$dumpvars
bx U
bx T
bx S
bx R
bx Q
bx P
bx O
bx N
bx M
bx L
bx K
bx J
bx I
bx H
bx G
bx F
1E
bx D
bx C
bx B
bx A
bx @
bx ?
bx >
bx =
bx <
bx ;
bx :
bx 9
bx 8
bx 7
x6
bx 5
bx 4
bx 3
bx 2
x1
x0
x/
x.
bx -
bx ,
bx +
bx *
bx )
bx (
bx '
bx &
bx %
bx $
bx #
bx "
x!
$end
#5000
b0 7
b0 9
b1 8
06
0E
#10000
b1 7
b10000010 C
b10000001 B
b10000000 A
b1000010 @
b1000001 ?
b1000000 >
b10 =
b1 <
b0 ;
b1000000 :
b1 9
1E
b11011 O
b1000000 D
16
#20000
06
#30000
b0 F
b10 7
16
#40000
06
#50000
b0 4
b0 G
b11 7
16
#60000
06
#70000
b0 2
b0 H
b100 7
16
#80000
06
#90000
b0 -
b0 I
b101 7
16
#100000
06
#110000
b0 J
b110 7
16
#120000
06
#130000
b0 ,
b0 K
b111 7
16
#140000
06
#150000
b0 3
b0 L
b1000 7
16
#160000
06
#170000
b11100101 #
10
b0 )
b0 R
b0 &
b0 P
01
b0 5
b0 %
b0 Q
b0 +
b0 M
b1001 7
16
#180000
06
#190000
0!
b11100101 "
1/
b0 *
b0 U
b0 $
b0 S
0.
b0 '
b0 T
b0 (
b0 N
b0 7
16
#200000
06
#210000
b1 7
b10000011 C
b10000010 B
b10000001 A
b1000011 @
b1000010 ?
b1000001 >
b11 =
b10 <
b1 ;
b10 9
16
#220000
06
#230000
b10 7
16
#240000
06
#250000
b11 7
16
#260000
06
#270000
b100 7
16
#280000
06
#290000
b101 7
16
#300000
06
#310000
b110 7
16
#320000
06
#330000
b111 7
16
#340000
06
#350000
b1000 7
16
#360000
06
#370000
b1001 7
16
#380000
06
#390000
b0 7
16
#400000
06
#410000
b1 7
b10000100 C
b10000011 B
b10000010 A
b1000100 @
b1000011 ?
b1000010 >
b100 =
b11 <
b10 ;
b11 9
16
#420000
06
#430000
b10 7
16
#440000
06
#450000
b11 7
16
#460000
06
#470000
b100 7
16
#480000
06
#490000
b101 7
16
#500000
06
#510000
b110 7
16
#520000
06
#530000
b111 7
16
#540000
06
#550000
b1000 7
16
#560000
06
#570000
b1001 7
16
#580000
06
#590000
b0 7
16
#600000
06
#610000
b1 7
b10000101 C
b10000100 B
b10000011 A
b1000101 @
b1000100 ?
b1000011 >
b101 =
b100 <
b11 ;
b100 9
16
#620000
06
#630000
b10 7
16
#640000
06
#650000
b11 7
16
#660000
06
#670000
b100 7
16
#680000
06
#690000
b101 7
16
#700000
06
#710000
b110 7
16
#720000
06
#730000
b111 7
16
#740000
06
#750000
b1000 7
16
#760000
06
#770000
b1001 7
16
#780000
06
#790000
b0 7
16
#800000
06
#810000
b1 7
b10000110 C
b10000101 B
b10000100 A
b1000110 @
b1000101 ?
b1000100 >
b110 =
b101 <
b100 ;
b101 9
16
#820000
06
#830000
b10 7
16
#840000
06
#850000
b11 7
16
#860000
06
#870000
b100 7
16
#880000
06
#890000
b101 7
16
#900000
06
#910000
b110 7
16
#920000
06
#930000
b111 7
16
#940000
06
#950000
b1000 7
16
#960000
06
#970000
b1001 7
16
#980000
06
#990000
b0 7
16
#1000000
06
#1010000
b1 7
b10000111 C
b10000110 B
b10000101 A
b1000111 @
b1000110 ?
b1000101 >
b111 =
b110 <
b101 ;
b110 9
16
#1020000
06
#1030000
b10 7
16
#1040000
06
#1050000
b11 7
16
#1060000
06
#1070000
b100 7
16
#1080000
06
#1090000
b101 7
16
#1100000
06
#1110000
b110 7
16
#1120000
06
#1130000
b111 7
16
#1140000
06
#1150000
b1000 7
16
#1160000
06
#1170000
b1001 7
16
#1180000
06
#1190000
b0 7
16
#1200000
06
#1210000
b1 7
b10001000 C
b10000111 B
b10000110 A
b1001000 @
b1000111 ?
b1000110 >
b1000 =
b111 <
b110 ;
b111 9
16
#1220000
06
#1230000
b10 7
16
#1240000
06
#1250000
b11 7
16
#1260000
06
#1270000
b100 7
16
#1280000
06
#1290000
b101 7
16
#1300000
06
#1310000
b110 7
16
#1320000
06
#1330000
b111 7
16
#1340000
06
#1350000
b1000 7
16
#1360000
06
#1370000
b1001 7
16
#1380000
06
#1390000
b0 7
16
#1400000
06
#1410000
b1 7
b10001001 C
b10001000 B
b10000111 A
b1001001 @
b1001000 ?
b1000111 >
b1001 =
b1000 <
b111 ;
b1000 9
16
#1420000
06
#1430000
b10 7
16
#1440000
06
#1450000
b11 7
16
#1460000
06
#1470000
b100 7
16
#1480000
06
#1490000
b101 7
16
#1500000
06
#1510000
b110 7
16
#1520000
06
#1530000
b111 7
16
#1540000
06
#1550000
b1000 7
16
#1560000
06
#1570000
b1001 7
16
#1580000
06
#1590000
b0 7
16
#1600000
06
#1610000
b1 7
b10001010 C
b10001001 B
b10001000 A
b1001010 @
b1001001 ?
b1001000 >
b1010 =
b1001 <
b1000 ;
b1001 9
16
#1620000
06
#1630000
b10 7
16
#1640000
06
#1650000
b11 7
16
#1660000
06
#1670000
b100 7
16
#1680000
06
#1690000
b101 7
16
#1700000
06
#1710000
b110 7
16
#1720000
06
#1730000
b111 7
16
#1740000
06
#1750000
b1000 7
16
#1760000
06
#1770000
b1001 7
16
#1780000
06
#1790000
b0 7
16
#1800000
06
#1810000
b1 7
b10001011 C
b10001010 B
b10001001 A
b1001011 @
b1001010 ?
b1001001 >
b1011 =
b1010 <
b1001 ;
b1010 9
16
#1820000
06
#1830000
b10 7
16
#1840000
06
#1850000
b11 7
16
#1860000
06
#1870000
b100 7
16
#1880000
06
#1890000
b101 7
16
#1900000
06
#1910000
b110 7
16
#1920000
06
#1930000
b111 7
16
#1940000
06
#1950000
b1000 7
16
#1960000
06
#1970000
b1001 7
16
#1980000
06
#1990000
b0 7
16
#2000000
06
#2010000
b1 7
b10001100 C
b10001011 B
b10001010 A
b1001100 @
b1001011 ?
b1001010 >
b1100 =
b1011 <
b1010 ;
b1011 9
16
#2020000
06
#2030000
b10 7
16
#2040000
06
#2050000
b11 7
16
#2060000
06
#2070000
b100 7
16
#2080000
06
#2090000
b101 7
16
#2100000
06
#2110000
b110 7
16
#2120000
06
#2130000
b111 7
16
#2140000
06
#2150000
b1000 7
16
#2160000
06
#2170000
b1001 7
16
#2180000
06
#2190000
b0 7
16
#2200000
06
#2210000
b1 7
b10001101 C
b10001100 B
b10001011 A
b1001101 @
b1001100 ?
b1001011 >
b1101 =
b1100 <
b1011 ;
b1100 9
16
#2220000
06
#2230000
b10 7
16
#2240000
06
#2250000
b11 7
16
#2260000
06
#2270000
b100 7
16
#2280000
06
#2290000
b101 7
16
#2300000
06
#2310000
b110 7
16
#2320000
06
#2330000
b111 7
16
#2340000
06
#2350000
b1000 7
16
#2360000
06
#2370000
b1001 7
16
#2380000
06
#2390000
b0 7
16
#2400000
06
#2410000
b1 7
b10001110 C
b10001101 B
b10001100 A
b1001110 @
b1001101 ?
b1001100 >
b1110 =
b1101 <
b1100 ;
b1101 9
16
#2420000
06
#2430000
b10 7
16
#2440000
06
#2450000
b11 7
16
#2460000
06
#2470000
b100 7
16
#2480000
06
#2490000
b101 7
16
#2500000
06
#2510000
b110 7
16
#2520000
06
#2530000
b111 7
16
#2540000
06
#2550000
b1000 7
16
#2560000
06
#2570000
b1001 7
16
#2580000
06
#2590000
b0 7
16
#2600000
06
#2610000
b1 7
b10001111 C
b10001110 B
b10001101 A
b1001111 @
b1001110 ?
b1001101 >
b1111 =
b1110 <
b1101 ;
b1110 9
16
#2620000
06
#2630000
b10 7
16
#2640000
06
#2650000
b11 7
16
#2660000
06
#2670000
b100 7
16
#2680000
06
#2690000
b101 7
16
#2700000
06
#2710000
b110 7
16
#2720000
06
#2730000
b111 7
16
#2740000
06
#2750000
b1000 7
16
#2760000
06
#2770000
b1001 7
16
#2780000
06
#2790000
b0 7
16
#2800000
06
#2810000
b1 7
b10010000 C
b10001111 B
b10001110 A
b1010000 @
b1001111 ?
b1001110 >
b10000 =
b1111 <
b1110 ;
b1111 9
16
#2820000
06
#2830000
b10 7
16
#2840000
06
#2850000
b11 7
16
#2860000
06
#2870000
b100 7
16
#2880000
06
#2890000
b101 7
16
#2900000
06
#2910000
b110 7
16
#2920000
06
#2930000
b111 7
16
#2940000
06
#2950000
b1000 7
16
#2960000
06
#2970000
b1001 7
16
#2980000
06
#2990000
b0 7
16
#3000000
06
#3010000
b1 7
b10010001 C
b10010000 B
b10001111 A
b1010001 @
b1010000 ?
b1001111 >
b10001 =
b10000 <
b1111 ;
b10000 9
16
#3020000
06
#3030000
b10 7
16
#3040000
06
#3050000
b11 7
16
#3060000
06
#3070000
b100 7
16
#3080000
06
#3090000
b101 7
16
#3100000
06
#3110000
b110 7
16
#3120000
06
#3130000
b111 7
16
#3140000
06
#3150000
b1000 7
16
#3160000
06
#3170000
b1001 7
16
#3180000
06
#3190000
b0 7
16
#3200000
06
#3210000
b1 7
b10010010 C
b10010001 B
b10010000 A
b1010010 @
b1010001 ?
b1010000 >
b10010 =
b10001 <
b10000 ;
b10001 9
16
#3220000
06
#3230000
b10 7
16
#3240000
06
#3250000
b11 7
16
#3260000
06
#3270000
b100 7
16
#3280000
06
#3290000
b101 7
16
#3300000
06
#3310000
b110 7
16
#3320000
06
#3330000
b111 7
16
#3340000
06
#3350000
b1000 7
16
#3360000
06
#3370000
b1001 7
16
#3380000
06
#3390000
1!
b10100110 "
0/
b11000001 *
b11000001 U
b11000001 $
b11000001 S
1.
b11000001 '
b11000001 T
b111111 (
b111111 N
b0 7
16
#3400000
06
#3410000
b1 7
b10010011 C
b10010010 B
b10010001 A
b1010011 @
b1010010 ?
b1010001 >
b10011 =
b10010 <
b10001 ;
b10010 9
16
#3420000
06
#3430000
b10 7
16
#3440000
06
#3450000
b11 7
16
#3460000
06
#3470000
b100 7
16
#3480000
06
#3490000
b101 7
16
#3500000
06
#3510000
b110 7
16
#3520000
06
#3530000
b111 7
16
#3540000
06
#3550000
b1000 7
16
#3560000
06
#3570000
b1100111 "
b10100110 #
00
b10000010 *
b10000010 U
b11000001 )
b11000001 R
b10000010 $
b10000010 S
b11000001 &
b11000001 P
11
b10000010 '
b10000010 T
b1111110 (
b111111 5
b11000001 %
b11000001 Q
b111111 +
b111111 M
b1001 7
16
#3580000
06
#3590000
b0 7
16
#3600000
06
#3610000
b1 7
b10010100 C
b10010011 B
b10010010 A
b1010100 @
b1010011 ?
b1010010 >
b10100 =
b10011 <
b10010 ;
b10011 9
16
#3620000
06
#3630000
b10 7
16
#3640000
06
#3650000
b11 7
16
#3660000
06
#3670000
b100 7
16
#3680000
06
#3690000
b101 7
16
#3700000
06
#3710000
b110 7
16
#3720000
06
#3730000
b101000 "
b11100101 #
10
b1000011 *
b1000011 U
b0 )
b0 R
b1000011 $
b1000011 S
b0 &
b0 P
01
b1000011 '
b1000011 T
b10111101 (
b1111110 5
b0 %
b0 Q
b111111 ,
b111111 K
b111 7
16
#3740000
06
#3750000
b10100110 #
00
b11000001 )
b11000001 R
b11000001 &
b11000001 P
11
b11000001 %
b11000001 Q
b1111110 +
b111111 3
b111111 L
b1000 7
16
#3760000
06
#3770000
b1001 7
16
#3780000
06
#3790000
b0 7
16
#3800000
06
#3810000
b1 7
b10010101 C
b10010100 B
b10010011 A
b1010101 @
b1010100 ?
b1010011 >
b10101 =
b10100 <
b10011 ;
b10100 9
16
#3820000
06
#3830000
b10 7
16
#3840000
06
#3850000
b11 7
16
#3860000
06
#3870000
b100 7
16
#3880000
06
#3890000
b101 7
16
#3900000
06
#3910000
b111111 J
b110 7
16
#3920000
06
#3930000
b111 7
16
#3940000
06
#3950000
b1000 7
16
#3960000
06
#3970000
b1001 7
16
#3980000
06
#3990000
b0 7
16
#4000000
06
#4010000
b1 7
b10010110 C
b10010101 B
b10010100 A
b1010110 @
b1010101 ?
b1010100 >
b10110 =
b10101 <
b10100 ;
b10101 9
16
#4020000
06
#4030000
b10 7
16
#4040000
06
#4050000
b11 7
16
#4060000
06
#4070000
b100 7
16
#4080000
06
#4090000
b1100111 #
b1100111 "
b10000010 )
b10000010 R
b10000010 *
b10000010 U
b10000010 &
b10000010 P
b10000010 $
b10000010 S
b10000010 %
b10000010 Q
b10111101 +
b1111110 3
b10000010 '
b10000010 T
b111111 -
b111111 I
b101 7
16
#4100000
06
#4110000
b110 7
16
#4120000
06
#4130000
b111 7
16
#4140000
06
#4150000
b1000 7
16
#4160000
06
#4170000
b1001 7
16
#4180000
06
#4190000
b0 7
16
#4200000
06
#4210000
b1 7
b10010111 C
b10010110 B
b10010101 A
b1010111 @
b1010110 ?
b1010101 >
b10111 =
b10110 <
b10101 ;
b10110 9
16
#4220000
06
#4230000
b10 7
16
#4240000
06
#4250000
b11 7
16
#4260000
06
#4270000
b100 7
16
#4280000
06
#4290000
b101 7
16
#4300000
06
#4310000
b110 7
16
#4320000
06
#4330000
b111 7
16
#4340000
06
#4350000
b1000 7
16
#4360000
06
#4370000
b1001 7
16
#4380000
06
#4390000
b0 7
16
#4400000
06
#4410000
b1 7
b10011000 C
b10010111 B
b10010110 A
b1011000 @
b1010111 ?
b1010110 >
b11000 =
b10111 <
b10110 ;
b10111 9
16
#4420000
06
#4430000
b10 7
16
#4440000
06
#4450000
b11 7
16
#4460000
06
#4470000
b10100110 #
b11000001 )
b11000001 R
b11000001 &
b11000001 P
b11000001 %
b11000001 Q
b1111110 ,
b111111 2
b111111 H
b100 7
16
#4480000
06
#4490000
b101 7
16
#4500000
06
#4510000
b110 7
16
#4520000
06
#4530000
b111 7
16
#4540000
06
#4550000
b1000 7
16
#4560000
06
#4570000
b1001 7
16
#4580000
06
#4590000
b0 7
16
#4600000
06
#4610000
b1 7
b10011001 C
b10011000 B
b10010111 A
b1011001 @
b1011000 ?
b1010111 >
b11001 =
b11000 <
b10111 ;
b11000 9
16
#4620000
06
#4630000
b10 7
16
#4640000
06
#4650000
b10100110 "
b11100101 #
10
b11000001 *
b11000001 U
b0 )
b0 R
b11000001 $
b11000001 S
b0 &
b0 P
01
b11000001 '
b11000001 T
b1111110 -
b111111 4
b0 %
b0 Q
b10111101 ,
b1111110 2
b111111 G
b11 7
16
#4660000
06
#4670000
b100 7
16
#4680000
06
#4690000
b101 7
16
#4700000
06
#4710000
b110 7
16
#4720000
06
#4730000
b111 7
16
#4740000
06
#4750000
b1000 7
16
#4760000
06
#4770000
b1001 7
16
#4780000
06
#4790000
b0 7
16
#4800000
06
#4810000
b1 7
b10011010 C
b10011001 B
b10011000 A
b1011010 @
b1011001 ?
b1011000 >
b11010 =
b11001 <
b11000 ;
b11001 9
16
#4820000
06
#4830000
0!
b11100101 "
1/
b0 *
b0 U
b0 $
b0 S
0.
b0 '
b0 T
b10111101 -
b1111110 4
b111111 F
b10 7
16
#4840000
06
#4850000
b11 7
16
#4860000
06
#4870000
b100 7
16
#4880000
06
#4890000
b101 7
16
#4900000
06
#4910000
b110 7
16
#4920000
06
#4930000
b111 7
16
#4940000
06
#4950000
b1000 7
16
#4960000
06
#4970000
b1001 7
16
#4980000
06
#4990000
b0 7
16
#5000000
06
#5010000
b1 7
b10011011 C
b10011010 B
b10011001 A
b1011011 @
b1011010 ?
b1011001 >
b11011 =
b11010 <
b11001 ;
b11010 9
16
#5020000
06
#5030000
b10 7
16
#5040000
06
#5050000
b11 7
16
#5060000
06
#5070000
b100 7
16
#5080000
06
#5090000
b101 7
16
#5100000
06
#5110000
b110 7
16
#5120000
06
#5130000
b111 7
16
#5140000
06
#5150000
b1000 7
16
#5160000
06
#5170000
b1001 7
16
#5180000
06
#5190000
b0 7
16
#5200000
06
#5210000
b1 7
b10011100 C
b10011011 B
b10011010 A
b1011100 @
b1011011 ?
b1011010 >
b11100 =
b11011 <
b11010 ;
b11011 9
16
#5220000
06
#5230000
b10 7
16
#5240000
06
#5250000
b11 7
16
#5260000
06
#5270000
b100 7
16
#5280000
06
#5290000
b101 7
16
#5300000
06
#5310000
b110 7
16
#5320000
06
#5330000
b111 7
16
#5340000
06
#5350000
b1000 7
16
#5360000
06
#5370000
b1001 7
16
#5380000
06
#5390000
b0 7
16
#5400000
06
#5410000
b1 7
b10011101 C
b10011100 B
b10011011 A
b1011101 @
b1011100 ?
b1011011 >
b11101 =
b11100 <
b11011 ;
b11100 9
16
#5420000
06
#5430000
b10 7
16
#5440000
06
#5450000
b11 7
16
#5460000
06
#5470000
b100 7
16
#5480000
06
#5490000
b101 7
16
#5500000
06
#5510000
b110 7
16
#5520000
06
#5530000
b111 7
16
#5540000
06
#5550000
b1000 7
16
#5560000
06
#5570000
b1001 7
16
#5580000
06
#5590000
b0 7
16
#5600000
06
#5610000
b1 7
b10011110 C
b10011101 B
b10011100 A
b1011110 @
b1011101 ?
b1011100 >
b11110 =
b11101 <
b11100 ;
b11101 9
16
#5620000
06
#5630000
b10 7
16
#5640000
06
#5650000
b11 7
16
#5660000
06
#5670000
b100 7
16
#5680000
06
#5690000
b101 7
16
#5700000
06
#5710000
b110 7
16
#5720000
06
#5730000
b111 7
16
#5740000
06
#5750000
b1000 7
16
#5760000
06
#5770000
b1001 7
16
#5780000
06
#5790000
b0 7
16
#5800000
06
#5810000
b1 7
b10011111 C
b10011110 B
b10011101 A
b1011111 @
b1011110 ?
b1011101 >
b11111 =
b11110 <
b11101 ;
b11110 9
16
#5820000
06
#5830000
b10 7
16
#5840000
06
#5850000
b11 7
16
#5860000
06
#5870000
b100 7
16
#5880000
06
#5890000
b101 7
16
#5900000
06
#5910000
b110 7
16
#5920000
06
#5930000
b111 7
16
#5940000
06
#5950000
b1000 7
16
#5960000
06
#5970000
b1001 7
16
#5980000
06
#5990000
b0 7
16
#6000000
06
#6010000
b1 7
b10100000 C
b10011111 B
b10011110 A
b1100000 @
b1011111 ?
b1011110 >
b100000 =
b11111 <
b11110 ;
b11111 9
16
#6020000
06
#6030000
b10 7
16
#6040000
06
#6050000
b11 7
16
#6060000
06
#6070000
b100 7
16
#6080000
06
#6090000
b101 7
16
#6100000
06
#6110000
b110 7
16
#6120000
06
#6130000
b111 7
16
#6140000
06
#6150000
b1000 7
16
#6160000
06
#6170000
b1001 7
16
#6180000
06
#6190000
b0 7
16
#6200000
06
#6210000
b1 7
b10100001 C
b10100000 B
b10011111 A
b1100001 @
b1100000 ?
b1011111 >
b100001 =
b100000 <
b11111 ;
b100000 9
16
#6220000
06
#6230000
b10 7
16
#6240000
06
#6250000
b11 7
16
#6260000
06
#6270000
b100 7
16
#6280000
06
#6290000
b101 7
16
#6300000
06
#6310000
b110 7
16
#6320000
06
#6330000
b111 7
16
#6340000
06
#6350000
b1000 7
16
#6360000
06
#6370000
b1001 7
16
#6380000
06
#6390000
b0 7
16
#6400000
06
#6410000
b1 7
b10100010 C
b10100001 B
b10100000 A
b1100010 @
b1100001 ?
b1100000 >
b100010 =
b100001 <
b100000 ;
b100001 9
16
#6420000
06
#6430000
b10 7
16
#6440000
06
#6450000
b11 7
16
#6460000
06
#6470000
b100 7
16
#6480000
06
#6490000
b101 7
16
#6500000
06
#6510000
b110 7
16
#6520000
06
#6530000
b111 7
16
#6540000
06
#6550000
b1000 7
16
#6560000
06
#6570000
b1001 7
16
#6580000
06
#6590000
b0 7
16
#6600000
06
#6610000
b1 7
b10100011 C
b10100010 B
b10100001 A
b1100011 @
b1100010 ?
b1100001 >
b100011 =
b100010 <
b100001 ;
b100010 9
16
#6620000
06
#6630000
b10 7
16
#6640000
06
#6650000
b11 7
16
#6660000
06
#6670000
b100 7
16
#6680000
06
#6690000
b101 7
16
#6700000
06
#6710000
b110 7
16
#6720000
06
#6730000
b111 7
16
#6740000
06
#6750000
b1000 7
16
#6760000
06
#6770000
b1001 7
16
#6780000
06
#6790000
b0 7
16
#6800000
06
#6810000
b1 7
b10100100 C
b10100011 B
b10100010 A
b1100100 @
b1100011 ?
b1100010 >
b100100 =
b100011 <
b100010 ;
b100011 9
16
#6820000
06
#6830000
b10 7
16
#6840000
06
#6850000
b11 7
16
#6860000
06
#6870000
b100 7
16
#6880000
06
#6890000
b101 7
16
#6900000
06
#6910000
b110 7
16
#6920000
06
#6930000
b111 7
16
#6940000
06
#6950000
b1000 7
16
#6960000
06
#6970000
b1001 7
16
#6980000
06
#6990000
b0 7
16
#7000000
06
#7010000
b1 7
b10100101 C
b10100100 B
b10100011 A
b1100101 @
b1100100 ?
b1100011 >
b100101 =
b100100 <
b100011 ;
b100100 9
16
#7020000
06
#7030000
b10 7
16
#7040000
06
#7050000
b11 7
16
#7060000
06
#7070000
b100 7
16
#7080000
06
#7090000
b101 7
16
#7100000
06
#7110000
b110 7
16
#7120000
06
#7130000
b111 7
16
#7140000
06
#7150000
b1000 7
16
#7160000
06
#7170000
b1001 7
16
#7180000
06
#7190000
b0 7
16
#7200000
06
#7210000
b1 7
b10100110 C
b10100101 B
b10100100 A
b1100110 @
b1100101 ?
b1100100 >
b100110 =
b100101 <
b100100 ;
b100101 9
16
#7220000
06
#7230000
b10 7
16
#7240000
06
#7250000
b11 7
16
#7260000
06
#7270000
b100 7
16
#7280000
06
#7290000
b101 7
16
#7300000
06
#7310000
b110 7
16
#7320000
06
#7330000
b111 7
16
#7340000
06
#7350000
b1000 7
16
#7360000
06
#7370000
b1001 7
16
#7380000
06
#7390000
b0 7
16
#7400000
06
#7410000
b1 7
b10100111 C
b10100110 B
b10100101 A
b1100111 @
b1100110 ?
b1100101 >
b100111 =
b100110 <
b100101 ;
b100110 9
16
#7420000
06
#7430000
b10 7
16
#7440000
06
#7450000
b11 7
16
#7460000
06
#7470000
b100 7
16
#7480000
06
#7490000
b101 7
16
#7500000
06
#7510000
b110 7
16
#7520000
06
#7530000
b111 7
16
#7540000
06
#7550000
b1000 7
16
#7560000
06
#7570000
b1001 7
16
#7580000
06
#7590000
b0 7
16
#7600000
06
#7610000
b1 7
b10101000 C
b10100111 B
b10100110 A
b1101000 @
b1100111 ?
b1100110 >
b101000 =
b100111 <
b100110 ;
b100111 9
16
#7620000
06
#7630000
b10 7
16
#7640000
06
#7650000
b11 7
16
#7660000
06
#7670000
1!
b10100110 #
00
b11000001 )
b11000001 R
b11000001 &
b11000001 P
11
b11000001 %
b11000001 Q
b1111110 ,
b111111 2
b0 H
b100 7
16
#7680000
06
#7690000
b101 7
16
#7700000
06
#7710000
b110 7
16
#7720000
06
#7730000
b111 7
16
#7740000
06
#7750000
b1000 7
16
#7760000
06
#7770000
b1001 7
16
#7780000
06
#7790000
b0 7
16
#7800000
06
#7810000
b1 7
b10101001 C
b10101000 B
b10100111 A
b1101001 @
b1101000 ?
b1100111 >
b101001 =
b101000 <
b100111 ;
b101000 9
16
#7820000
06
#7830000
b10 7
16
#7840000
06
