Semester Project/get_Index.v

// of no use fil hal
module get_Index(clk,
                 i,
                 j,
                 l0,
                 l1,
                 l2,
                 l3,
                 l4,
                 l5,
                 l6,
                 l7,
                 l8);
    input clk;
    input [5:0] i, j;
    output reg [11:0] l0,l1,l2,l3,l4,l5,l6,l7,l8;
    parameter n = 64;
    reg k;
    always@(posedge clk)
    begin
        k  = 0 + (i * n);
        l0 = k - n + j - 1;
        l1 = k - n + j;
        l2 = k - n + (j + 1);
        l3 = k + (j - 1);
        l4 = k + j;
        l5 = k + (j + 1);
        l6 = k + n + (j - 1);
        l7 = k + n + j;
        l8 = k + n + (j + 1);
        $monitor("%0d", l0, l1, l2, l3, l4, l5, l6, l7,l8);
    end
endmodule

Semester Project/sobel.v
// `include "get_Index.v"
module sobel();
    // https://timetoexplore.net/blog/initialize-memory-in-verilog
    reg [7:0] ROM_IN  [0:4095];  // = > 64*64 - 1 = > sizeofimage - 1
    reg [7:0] ROM_OUT [0:4095];
    reg clk;
    reg [6:0] i, j, n;
    
    reg [12:0] k,l0,l1,l2,l3,l4,l5,l6,l7,l8;
    
    initial
    begin
        $dumpfile("sobel.vcd");
        $dumpvars(0, sobel);
        clk = 0;
        i   = 1;
        j   = 0;
        n   = 64;
        t   = 27;
        // reading from in.txt and saving in ROM_IN from address 0 to 4095
        $readmemb ("in.txt", ROM_IN, 0, 4095);
        // $monitor("data_file handle was %0b", ROM_IN[38]);
        // writing to out.txt from ROM_IN from address 0 to 4095
        // $writememb("out.txt",ROM_OUT);
        
    end
    
    always@(posedge clk)
    begin
        j = j+1;
        if (j > 64-2)
        begin
            j = 1;
            i = i + 1;
            if (i > 64-2)
            begin
                i = 1;
                $writememb("out.txt",ROM_OUT);
                $finish();
            end
        end
        k  = 0 + (i * n);
        l0 = k - n + j - 1;
        l1 = k - n + j;
        l2 = k - n + (j + 1);
        l3 = k + (j - 1);
        l4 = k + j;
        l5 = k + (j + 1);
        l6 = k + n + (j - 1);
        l7 = k + n + j;
        l8 = k + n + (j + 1);
        
        
    end
    
    always // to generate clock
    begin
    #10
    clk = !clk;
    end
    
    reg [7:0] t;
    reg [7:0]s0,s1,s2,s3,s4,s5,s6,s7,s8;
    output wire d;
    wire [7:0]a0,a1,a2,a3;
    wire [7:0]f9,f10,f11,f12,f13,f14;
    wire [7:0]g1,g2,g3,g4;
    wire c2,c5,c3,c4;
    wire [7:0]tem1,tem2;
    
    
    
    always@(posedge clk)
    begin
        s0 = ROM_IN[l0]>>2;
        s1 = ROM_IN[l1]>>2;
        s2 = ROM_IN[l2]>>2;
        s3 = ROM_IN[l3]>>2;
        s4 = ROM_IN[l4]>>2;
        s5 = ROM_IN[l5]>>2;
        s6 = ROM_IN[l6]>>2;
        s7 = ROM_IN[l7]>>2;
        s8 = ROM_IN[l8]>>2;
        
        
    end
    
    assign    a1 = s0+s1;
    assign    a3 = s1+s2;
    assign    a2 = s3+s6;
    assign   a0  = s5+s7;
    assign   f10 = a1+s3;
    assign   f11 = a3+s5;
    assign   f12 = a2+s7;
    assign   f9  = a0+s8;
    
    assign  g1         = f10-f9;
    assign  g3         = f11-f12;
    assign  {c2, g2}   = f11-f12;
    assign  {c5, g4}   = f10-f9;
    assign  {c3, tem1} = f14-t;
    assign  {c4, tem2} = f13-t;
    
    mux_2_1 ob1(g2,g3,c2,f14);
    mux_2_1 ob2(g4,g1,c5,f13);
    
    assign d = ~(c3&c4);
    always@(*)
        ROM_OUT[l4] = d;
    
endmodule
    
    module mux_2_1(a,b,s,out);
        input[7:0] a,b;
        input s;
        output[7:0] out;
        reg[7:0] out;
        
        always@ (*)
        begin
            if (s == 0)
            begin
                out <= a;
            end
            else
            begin
                out <= b;
            end
        end
    endmodule
        
        // In order to read and write a file following commands are used in Verilog.
        // •	Reading a file in Verilog
        // reg [<memory_width>] <reg_name> [<memory_depth>];
        
        // initial
        // $readmemb ("<file_name>", <reg_name>, <start_address>, <end_address>);
        
        // •	Writing a file in verilog
        // always@(posedge	 clk)
        // $fwrite(<file_desc>, "%d", out);
        // initial
        // File_desc = $fopen(“filename.txt”,w);
        
        // integer id;
        // initial
        // Id = $fopen(“File path and name”, mode);	//here mode = “w”
        
        // always@(posedge clk)
        // begin
        //for reading sample by sample data and writing data into file
        // for file writing using following syntax
        // $fwrite(id, out);
        // $fwrite(id, “\n”); 	//for newline
        // end
        
        
        // ________________
        // | P0 | P1 | P2 |     --------> n columns
        // |----|----|----|     |
        // | P3 | P4 | P5 |     |
        // |----|----|----|     |
        // | P6 | P7 | P8 |     m rows
        // ----------------
        
        // | P0 |
        // | P1 |
        // | P2 |
        // | P3 |
        // | P4 |
        // | P5 |
        // | P6 |
        // | P7 |
        // | P8 |
        // row major
        
        // Variable ‘i’ represents row number whereas j represents column number
        // Variable ‘B’ is the base address of the array
        // Variable ‘n’ is the total number of the column of an image
        
        // get_Index obj(clk,i,j,l0,l1,l2,l3,l4,l5,l6,l7,l8);

Semester Project/sobel.vcd
$date
	Tue Dec 24 01:52:16 2019
$end
$version
	Icarus Verilog
$end
$timescale
	1s
$end
$scope module sobel $end
$var wire 1 ! d $end
$var wire 8 " tem2 [7:0] $end
$var wire 8 # tem1 [7:0] $end
$var wire 8 $ g4 [7:0] $end
$var wire 8 % g3 [7:0] $end
$var wire 8 & g2 [7:0] $end
$var wire 8 ' g1 [7:0] $end
$var wire 8 ( f9 [7:0] $end
$var wire 8 ) f14 [7:0] $end
$var wire 8 * f13 [7:0] $end
$var wire 8 + f12 [7:0] $end
$var wire 8 , f11 [7:0] $end
$var wire 8 - f10 [7:0] $end
$var wire 1 . c5 $end
$var wire 1 / c4 $end
$var wire 1 0 c3 $end
$var wire 1 1 c2 $end
$var wire 8 2 a3 [7:0] $end
$var wire 8 3 a2 [7:0] $end
$var wire 8 4 a1 [7:0] $end
$var wire 8 5 a0 [7:0] $end
$var reg 1 6 clk $end
$var reg 7 7 i [6:0] $end
$var reg 7 8 j [6:0] $end
$var reg 13 9 k [12:0] $end
$var reg 13 : l0 [12:0] $end
$var reg 13 ; l1 [12:0] $end
$var reg 13 < l2 [12:0] $end
$var reg 13 = l3 [12:0] $end
$var reg 13 > l4 [12:0] $end
$var reg 13 ? l5 [12:0] $end
$var reg 13 @ l6 [12:0] $end
$var reg 13 A l7 [12:0] $end
$var reg 13 B l8 [12:0] $end
$var reg 7 C n [6:0] $end
$var reg 8 D s0 [7:0] $end
$var reg 8 E s1 [7:0] $end
$var reg 8 F s2 [7:0] $end
$var reg 8 G s3 [7:0] $end
$var reg 8 H s4 [7:0] $end
$var reg 8 I s5 [7:0] $end
$var reg 8 J s6 [7:0] $end
$var reg 8 K s7 [7:0] $end
$var reg 8 L s8 [7:0] $end
$var reg 8 M t [7:0] $end
$scope module ob1 $end
$var wire 8 N a [7:0] $end
$var wire 8 O b [7:0] $end
$var wire 1 1 s $end
$var reg 8 P out [7:0] $end
$upscope $end
$scope module ob2 $end
$var wire 8 Q a [7:0] $end
$var wire 8 R b [7:0] $end
$var wire 1 . s $end
$var reg 8 S out [7:0] $end
$upscope $end
$upscope $end
$enddefinitions $end
#0
$dumpvars
bx S
bx R
bx Q
bx P
bx O
bx N
b11011 M
bx L
bx K
bx J
bx I
bx H
bx G
bx F
bx E
bx D
b1000000 C
bx B
bx A
bx @
bx ?
bx >
bx =
bx <
bx ;
bx :
bx 9
b0 8
b1 7
06
bx 5
bx 4
bx 3
bx 2
x1
x0
x/
x.
bx -
bx ,
bx +
bx *
bx )
bx (
bx '
bx &
bx %
bx $
bx #
bx "
x!
$end
#10
b10000010 B
b10000001 A
b10000000 @
b1000010 ?
b1000001 >
b1000000 =
b10 <
b1 ;
b0 :
b1000000 9
b1 8
b0xxxxxx L
b0xxxxxx K
b0xxxxxx J
b0xxxxxx I
b0xxxxxx H
b0xxxxxx G
b0xxxxxx F
b0xxxxxx E
b0xxxxxx D
16
#20
06
#30
0!
b11100101 "
1/
b11100101 #
10
b0 *
b0 S
b0 )
b0 P
b0 $
b0 Q
0.
b0 &
b0 N
01
b0 '
b0 R
b0 (
b0 L
b0 5
b0 %
b0 O
b0 +
b0 K
b0 3
b0 J
b0 ,
b0 I
b0 H
b0 -
b0 G
b0 2
b0 F
b0 4
b0 E
b0 D
b10000011 B
b10000010 A
b10000001 @
b1000011 ?
b1000010 >
b1000001 =
b11 <
b10 ;
b1 :
b10 8
16
#40
06
#50
b10000100 B
b10000011 A
b10000010 @
b1000100 ?
b1000011 >
b1000010 =
b100 <
b11 ;
b10 :
b11 8
16
#60
06
#70
b10000101 B
b10000100 A
b10000011 @
b1000101 ?
b1000100 >
b1000011 =
b101 <
b100 ;
b11 :
b100 8
16
#80
06
#90
b10000110 B
b10000101 A
b10000100 @
b1000110 ?
b1000101 >
b1000100 =
b110 <
b101 ;
b100 :
b101 8
16
#100
06
#110
b10000111 B
b10000110 A
b10000101 @
b1000111 ?
b1000110 >
b1000101 =
b111 <
b110 ;
b101 :
b110 8
16
#120
06
#130
b10001000 B
b10000111 A
b10000110 @
b1001000 ?
b1000111 >
b1000110 =
b1000 <
b111 ;
b110 :
b111 8
16
#140
06
#150
b10001001 B
b10001000 A
b10000111 @
b1001001 ?
b1001000 >
b1000111 =
b1001 <
b1000 ;
b111 :
b1000 8
16
#160
06
#170
b10001010 B
b10001001 A
b10001000 @
b1001010 ?
b1001001 >
b1001000 =
b1010 <
b1001 ;
b1000 :
b1001 8
16
#180
06
#190
b10001011 B
b10001010 A
b10001001 @
b1001011 ?
b1001010 >
b1001001 =
b1011 <
b1010 ;
b1001 :
b1010 8
16
#200
06
#210
b10001100 B
b10001011 A
b10001010 @
b1001100 ?
b1001011 >
b1001010 =
b1100 <
b1011 ;
b1010 :
b1011 8
16
#220
06
#230
b10001101 B
b10001100 A
b10001011 @
b1001101 ?
b1001100 >
b1001011 =
b1101 <
b1100 ;
b1011 :
b1100 8
16
#240
06
#250
b10001110 B
b10001101 A
b10001100 @
b1001110 ?
b1001101 >
b1001100 =
b1110 <
b1101 ;
b1100 :
b1101 8
16
#260
06
#270
b10001111 B
b10001110 A
b10001101 @
b1001111 ?
b1001110 >
b1001101 =
b1111 <
b1110 ;
b1101 :
b1110 8
16
#280
06
#290
b10010000 B
b10001111 A
b10001110 @
b1010000 ?
b1001111 >
b1001110 =
b10000 <
b1111 ;
b1110 :
b1111 8
16
#300
06
#310
b10010001 B
b10010000 A
b10001111 @
b1010001 ?
b1010000 >
b1001111 =
b10001 <
b10000 ;
b1111 :
b10000 8
16
#320
06
#330
b10010010 B
b10010001 A
b10010000 @
b1010010 ?
b1010001 >
b1010000 =
b10010 <
b10001 ;
b10000 :
b10001 8
16
#340
06
#350
1!
b1100111 "
0/
b10100110 #
00
b10000010 *
b10000010 S
b11000001 )
b11000001 P
b10000010 $
b10000010 Q
1.
b11000001 &
b11000001 N
11
b111111 L
b10000010 '
b10000010 R
b1111110 (
b111111 5
b11000001 %
b11000001 O
b111111 +
b111111 K
b10010011 B
b10010010 A
b10010001 @
b1010011 ?
b1010010 >
b1010001 =
b10011 <
b10010 ;
b10001 :
b10010 8
16
#360
06
#370
b10010100 B
b10010011 A
b10010010 @
b1010100 ?
b1010011 >
b1010010 =
b10100 <
b10011 ;
b10010 :
b10011 8
16
#380
06
#390
b101000 "
b1000011 *
b1000011 S
b1000011 $
b1000011 Q
b1111110 +
b111111 3
b111111 J
b1000011 '
b1000011 R
b10111101 (
b1111110 5
b11000001 %
b11000001 O
b111111 ,
b111111 I
b111111 H
b10010101 B
b10010100 A
b10010011 @
b1010101 ?
b1010100 >
b1010011 =
b10101 <
b10100 ;
b10011 :
b10100 8
16
#400
06
#410
b10010110 B
b10010101 A
b10010100 @
b1010110 ?
b1010101 >
b1010100 =
b10110 <
b10101 ;
b10100 :
b10101 8
16
#420
06
#430
b1100111 #
b1100111 "
b10000010 )
b10000010 P
b10000010 *
b10000010 S
b10000010 &
b10000010 N
b10000010 $
b10000010 Q
b10000010 %
b10000010 O
b10111101 +
b1111110 3
b10000010 '
b10000010 R
b111111 -
b111111 G
b10010111 B
b10010110 A
b10010101 @
b1010111 ?
b1010110 >
b1010101 =
b10111 <
b10110 ;
b10101 :
b10110 8
16
#440
06
#450
b10011000 B
b10010111 A
b10010110 @
b1011000 ?
b1010111 >
b1010110 =
b11000 <
b10111 ;
b10110 :
b10111 8
16
#460
06
#470
b10100110 "
b11100101 #
10
b11000001 *
b11000001 S
b0 )
b0 P
01
b11000001 $
b11000001 Q
b0 &
b0 N
b111111 F
b11000001 '
b11000001 R
b1111110 -
b111111 4
b0 %
b0 O
b10111101 ,
b1111110 2
b111111 E
b10011001 B
b10011000 A
b10010111 @
b1011001 ?
b1011000 >
b1010111 =
b11001 <
b11000 ;
b10111 :
b11000 8
16
#480
06
#490
b10011010 B
b10011001 A
b10011000 @
b1011010 ?
b1011001 >
b1011000 =
b11010 <
b11001 ;
b11000 :
b11001 8
16
#500
06
#510
0!
b11100101 "
1/
b0 *
b0 S
b0 $
b0 Q
0.
b0 '
b0 R
b10111101 -
b1111110 4
b111111 D
b10011011 B
b10011010 A
b10011001 @
b1011011 ?
b1011010 >
b1011001 =
b11011 <
b11010 ;
b11001 :
b11010 8
16
#520
06
#530
b10011100 B
b10011011 A
b10011010 @
b1011100 ?
b1011011 >
b1011010 =
b11100 <
b11011 ;
b11010 :
b11011 8
16
#540
06
#550
b10011101 B
b10011100 A
b10011011 @
b1011101 ?
b1011100 >
b1011011 =
b11101 <
b11100 ;
b11011 :
b11100 8
16
#560
06
#570
b10011110 B
b10011101 A
b10011100 @
b1011110 ?
b1011101 >
b1011100 =
b11110 <
b11101 ;
b11100 :
b11101 8
16
#580
06
#590
b10011111 B
b10011110 A
b10011101 @
b1011111 ?
b1011110 >
b1011101 =
b11111 <
b11110 ;
b11101 :
b11110 8
16
#600
06
#610
b10100000 B
b10011111 A
b10011110 @
b1100000 ?
b1011111 >
b1011110 =
b100000 <
b11111 ;
b11110 :
b11111 8
16
#620
06
#630
b10100001 B
b10100000 A
b10011111 @
b1100001 ?
b1100000 >
b1011111 =
b100001 <
b100000 ;
b11111 :
b100000 8
16
#640
06
#650
b10100010 B
b10100001 A
b10100000 @
b1100010 ?
b1100001 >
b1100000 =
b100010 <
b100001 ;
b100000 :
b100001 8
16
#660
06
#670
b10100011 B
b10100010 A
b10100001 @
b1100011 ?
b1100010 >
b1100001 =
b100011 <
b100010 ;
b100001 :
b100010 8
16
#680
06
#690
b10100100 B
b10100011 A
b10100010 @
b1100100 ?
b1100011 >
b1100010 =
b100100 <
b100011 ;
b100010 :
b100011 8
16
#700
06
#710
b10100101 B
b10100100 A
b10100011 @
b1100101 ?
b1100100 >
b1100011 =
b100101 <
b100100 ;
b100011 :
b100100 8
16
#720
06
#730
b10100110 B
b10100101 A
b10100100 @
b1100110 ?
b1100101 >
b1100100 =
b100110 <
b100101 ;
b100100 :
b100101 8
16
#740
06
#750
b10100111 B
b10100110 A
b10100101 @
b1100111 ?
b1100110 >
b1100101 =
b100111 <
b100110 ;
b100101 :
b100110 8
16
#760
06
#770
b10101000 B
b10100111 A
b10100110 @
b1101000 ?
b1100111 >
b1100110 =
b101000 <
b100111 ;
b100110 :
b100111 8
16
#780
06
#790
1!
b10100110 "
0/
b1100111 #
00
b11000001 *
b11000001 S
b10000010 )
b10000010 P
b11000001 $
b11000001 Q
1.
b10000010 &
b10000010 N
11
b0 F
b11000001 '
b11000001 R
b1111110 -
b111111 4
b10000010 %
b10000010 O
b111111 ,
b0 2
b0 E
b10101001 B
b10101000 A
b10100111 @
b1101001 ?
b1101000 >
b1100111 =
b101001 <
b101000 ;
b100111 :
b101000 8
16
#800
06
#810
b10101010 B
b10101001 A
b10101000 @
b1101010 ?
b1101001 >
b1101000 =
b101010 <
b101001 ;
b101000 :
b101001 8
16
#820
06
#830
b1100111 "
b10000010 *
b10000010 S
b10000010 $
b10000010 Q
b10000010 '
b10000010 R
b111111 -
b0 4
b0 D
b10101011 B
b10101010 A
b10101001 @
b1101011 ?
b1101010 >
b1101001 =
b101011 <
b101010 ;
b101001 :
b101010 8
16
#840
06
#850
b10101100 B
b10101011 A
b10101010 @
b1101100 ?
b1101011 >
b1101010 =
b101100 <
b101011 ;
b101010 :
b101011 8
16
#860
06
#870
b10100110 "
b101000 #
b11000001 *
b11000001 S
b1000011 )
b1000011 P
b11000001 $
b11000001 Q
b1000011 &
b1000011 N
b11000001 '
b11000001 R
b1111110 (
b111111 5
b1000011 %
b1000011 O
b0 ,
b0 I
b0 H
b10101101 B
b10101100 A
b10101011 @
b1101101 ?
b1101100 >
b1101011 =
b101101 <
b101100 ;
b101011 :
b101100 8
16
#880
06
#890
b10101110 B
b10101101 A
b10101100 @
b1101110 ?
b1101101 >
b1101100 =
b101110 <
b101101 ;
b101100 :
b101101 8
16
#900
06
#910
b10100110 #
b11100101 "
1/
b11000001 )
b11000001 P
b0 *
b0 S
0.
b11000001 &
b11000001 N
b0 $
b0 Q
b0 L
b0 (
b0 5
b0 K
b11000001 %
b11000001 O
b111111 +
b111111 3
b0 '
b0 R
b0 -
b0 G
b10101111 B
b10101110 A
b10101101 @
b1101111 ?
b1101110 >
b1101101 =
b101111 <
b101110 ;
b101101 :
b101110 8
16
#920
06
#930
b10110000 B
b10101111 A
b10101110 @
b1110000 ?
b1101111 >
b1101110 =
b110000 <
b101111 ;
b101110 :
b101111 8
16
#940
06
#950
0!
b11100101 #
10
b0 )
b0 P
b0 &
b0 N
01
b0 %
b0 O
b0 +
b0 3
b0 J
b10110001 B
b10110000 A
b10101111 @
b1110001 ?
b1110000 >
b1101111 =
b110001 <
b110000 ;
b101111 :
b110000 8
16
#960
06
#970
b10110010 B
b10110001 A
b10110000 @
b1110010 ?
b1110001 >
b1110000 =
b110010 <
b110001 ;
b110000 :
b110001 8
16
#980
06
#990
b10110011 B
b10110010 A
b10110001 @
b1110011 ?
b1110010 >
b1110001 =
b110011 <
b110010 ;
b110001 :
b110010 8
16
#1000
06
#1010
b10110100 B
b10110011 A
b10110010 @
b1110100 ?
b1110011 >
b1110010 =
b110100 <
b110011 ;
b110010 :
b110011 8
16
#1020
06
#1030
b10110101 B
b10110100 A
b10110011 @
b1110101 ?
b1110100 >
b1110011 =
b110101 <
b110100 ;
b110011 :
b110100 8
16
#1040
06
#1050
b10110110 B
b10110101 A
b10110100 @
b1110110 ?
b1110101 >
b1110100 =
b110110 <
b110101 ;
b110100 :
b110101 8
16
#1060
06
#1070
b10110111 B
b10110110 A
b10110101 @
b1110111 ?
b1110110 >
b1110101 =
b110111 <
b110110 ;
b110101 :
b110110 8
16
#1080
06
#1090
b10111000 B
b10110111 A
b10110110 @
b1111000 ?
b1110111 >
b1110110 =
b111000 <
b110111 ;
b110110 :
b110111 8
16
#1100
06
#1110
b10111001 B
b10111000 A
b10110111 @
b1111001 ?
b1111000 >
b1110111 =
b111001 <
b111000 ;
b110111 :
b111000 8
16
#1120
06
#1130
b10111010 B
b10111001 A
b10111000 @
b1111010 ?
b1111001 >
b1111000 =
b111010 <
b111001 ;
b111000 :
b111001 8
16
#1140
06
#1150
b10111011 B
b10111010 A
b10111001 @
b1111011 ?
b1111010 >
b1111001 =
b111011 <
b111010 ;
b111001 :
b111010 8
16
#1160
06
#1170
b10111100 B
b10111011 A
b10111010 @
b1111100 ?
b1111011 >
b1111010 =
b111100 <
b111011 ;
b111010 :
b111011 8
16
#1180
06
#1190
b10111101 B
b10111100 A
b10111011 @
b1111101 ?
b1111100 >
b1111011 =
b111101 <
b111100 ;
b111011 :
b111100 8
16
#1200
06
#1210
b10111110 B
b10111101 A
b10111100 @
b1111110 ?
b1111101 >
b1111100 =
b111110 <
b111101 ;
b111100 :
b111101 8
16
#1220
06
#1230
b10111111 B
b10111110 A
b10111101 @
b1111111 ?
b1111110 >
b1111101 =
b111111 <
b111110 ;
b111101 :
b111110 8
16
#1240
06
#1250
b11000010 B
b11000001 A
b11000000 @
b10000010 ?
b10000001 >
b10000000 =
b1000010 <
b1000001 ;
b1000000 :
b10000000 9
b10 7
b1 8
16
#1260
06
#1270
b11000011 B
b11000010 A
b11000001 @
b10000011 ?
b10000010 >
b10000001 =
b1000011 <
b1000010 ;
b1000001 :
b10 8
16
#1280
06
#1290
b11000100 B
b11000011 A
b11000010 @
b10000100 ?
b10000011 >
b10000010 =
b1000100 <
b1000011 ;
b1000010 :
b11 8
16
#1300
06
#1310
b11000101 B
b11000100 A
b11000011 @
b10000101 ?
b10000100 >
b10000011 =
b1000101 <
b1000100 ;
b1000011 :
b100 8
16
#1320
06
#1330
b11000110 B
b11000101 A
b11000100 @
b10000110 ?
b10000101 >
b10000100 =
b1000110 <
b1000101 ;
b1000100 :
b101 8
16
#1340
06
#1350
b11000111 B
b11000110 A
b11000101 @
b10000111 ?
b10000110 >
b10000101 =
b1000111 <
b1000110 ;
b1000101 :
b110 8
16
#1360
06
#1370
b11001000 B
b11000111 A
b11000110 @
b10001000 ?
b10000111 >
b10000110 =
b1001000 <
b1000111 ;
b1000110 :
b111 8
16
#1380
06
#1390
b11001001 B
b11001000 A
b11000111 @
b10001001 ?
b10001000 >
b10000111 =
b1001001 <
b1001000 ;
b1000111 :
b1000 8
16
#1400
06
#1410
b11001010 B
b11001001 A
b11001000 @
b10001010 ?
b10001001 >
b10001000 =
b1001010 <
b1001001 ;
b1001000 :
b1001 8
16
#1420
06
#1430
b11001011 B
b11001010 A
b11001001 @
b10001011 ?
b10001010 >
b10001001 =
b1001011 <
b1001010 ;
b1001001 :
b1010 8
16
#1440
06
#1450
b11001100 B
b11001011 A
b11001010 @
b10001100 ?
b10001011 >
b10001010 =
b1001100 <
b1001011 ;
b1001010 :
b1011 8
16
#1460
06
#1470
b11001101 B
b11001100 A
b11001011 @
b10001101 ?
b10001100 >
b10001011 =
b1001101 <
b1001100 ;
b1001011 :
b1100 8
16
#1480
06
#1490
b11001110 B
b11001101 A
b11001100 @
b10001110 ?
b10001101 >
b10001100 =
b1001110 <
b1001101 ;
b1001100 :
b1101 8
16
#1500
06
#1510
b11001111 B
b11001110 A
b11001101 @
b10001111 ?
b10001110 >
b10001101 =
b1001111 <
b1001110 ;
b1001101 :
b1110 8
16
#1520
06
#1530
b11010000 B
b11001111 A
b11001110 @
b10010000 ?
b10001111 >
b10001110 =
b1010000 <
b1001111 ;
b1001110 :
b1111 8
16
#1540
06
#1550
1!
b1100111 "
0/
b10100110 #
00
b10000010 *
b10000010 S
b11000001 )
b11000001 P
b10000010 $
b10000010 Q
1.
b11000001 &
b11000001 N
11
b111111 L
b10000010 '
b10000010 R
b1111110 (
b111111 5
b11000001 %
b11000001 O
b111111 +
b111111 K
b11010001 B
b11010000 A
b11001111 @
b10010001 ?
b10010000 >
b10001111 =
b1010001 <
b1010000 ;
b1001111 :
b10000 8
16
#1560
06
#1570
b11010010 B
b11010001 A
b11010000 @
b10010010 ?
b10010001 >
b10010000 =
b1010010 <
b1010001 ;
b1010000 :
b10001 8
16
#1580
06
#1590
b101000 "
b1000011 *
b1000011 S
b1000011 $
b1000011 Q
b1111110 +
b111111 3
b111111 J
b1000011 '
b1000011 R
b10111101 (
b1111110 5
b11000001 %
b11000001 O
b111111 ,
b111111 I
b111111 H
b11010011 B
b11010010 A
b11010001 @
b10010011 ?
b10010010 >
b10010001 =
b1010011 <
b1010010 ;
b1010001 :
b10010 8
16
#1600
06
#1610
b11010100 B
b11010011 A
b11010010 @
b10010100 ?
b10010011 >
b10010010 =
b1010100 <
b1010011 ;
b1010010 :
b10011 8
16
#1620
06
#1630
b10100110 "
b11100101 #
10
b11000001 *
b11000001 S
b0 )
b0 P
b11000001 $
b11000001 Q
b0 &
b0 N
01
b10111101 +
b1111110 3
b111111 G
b111111 F
b11000001 '
b11000001 R
b1111110 -
b111111 4
b0 %
b0 O
b10111101 ,
b1111110 2
b111111 E
b11010101 B
b11010100 A
b11010011 @
b10010101 ?
b10010100 >
b10010011 =
b1010101 <
b1010100 ;
b1010011 :
b10100 8
16
#1640
06
#1650
b11010110 B
b11010101 A
b11010100 @
b10010110 ?
b10010101 >
b10010100 =
b1010110 <
b1010101 ;
b1010100 :
b10101 8
16
#1660
06
#1670
0!
b11100101 "
1/
b0 *
b0 S
b0 $
b0 Q
0.
b0 '
b0 R
b10111101 -
b1111110 4
b111111 D
b11010111 B
b11010110 A
b11010101 @
b10010111 ?
b10010110 >
b10010101 =
b1010111 <
b1010110 ;
b1010101 :
b10110 8
16
#1680
06
#1690
b11011000 B
b11010111 A
b11010110 @
b10011000 ?
b10010111 >
b10010110 =
b1011000 <
b1010111 ;
b1010110 :
b10111 8
16
#1700
06
#1710
b11011001 B
b11011000 A
b11010111 @
b10011001 ?
b10011000 >
b10010111 =
b1011001 <
b1011000 ;
b1010111 :
b11000 8
16
#1720
06
#1730
b11011010 B
b11011001 A
b11011000 @
b10011010 ?
b10011001 >
b10011000 =
b1011010 <
b1011001 ;
b1011000 :
b11001 8
16
#1740
06
#1750
b11011011 B
b11011010 A
b11011001 @
b10011011 ?
b10011010 >
b10011001 =
b1011011 <
b1011010 ;
b1011001 :
b11010 8
16
#1760
06
#1770
b11011100 B
b11011011 A
b11011010 @
b10011100 ?
b10011011 >
b10011010 =
b1011100 <
b1011011 ;
b1011010 :
b11011 8
16
#1780
06
#1790
b11011101 B
b11011100 A
b11011011 @
b10011101 ?
b10011100 >
b10011011 =
b1011101 <
b1011100 ;
b1011011 :
b11100 8
16
#1800
06
#1810
b11011110 B
b11011101 A
b11011100 @
b10011110 ?
b10011101 >
b10011100 =
b1011110 <
b1011101 ;
b1011100 :
b11101 8
16
#1820
06
#1830
b11011111 B
b11011110 A
b11011101 @
b10011111 ?
b10011110 >
b10011101 =
b1011111 <
b1011110 ;
b1011101 :
b11110 8
16
#1840
06
#1850
b11100000 B
b11011111 A
b11011110 @
b10100000 ?
b10011111 >
b10011110 =
b1100000 <
b1011111 ;
b1011110 :
b11111 8
16
#1860
06
#1870
b11100001 B
b11100000 A
b11011111 @
b10100001 ?
b10100000 >
b10011111 =
b1100001 <
b1100000 ;
b1011111 :
b100000 8
16
#1880
06
#1890
b11100010 B
b11100001 A
b11100000 @
b10100010 ?
b10100001 >
b10100000 =
b1100010 <
b1100001 ;
b1100000 :
b100001 8
16
#1900
06
#1910
b11100011 B
b11100010 A
b11100001 @
b10100011 ?
b10100010 >
b10100001 =
b1100011 <
b1100010 ;
b1100001 :
b100010 8
16
#1920
06
#1930
b11100100 B
b11100011 A
b11100010 @
b10100100 ?
b10100011 >
b10100010 =
b1100100 <
b1100011 ;
b1100010 :
b100011 8
16
#1940
06
#1950
b11100101 B
b11100100 A
b11100011 @
b10100101 ?
b10100100 >
b10100011 =
b1100101 <
b1100100 ;
b1100011 :
b100100 8
16
#1960
06
#1970
b11100110 B
b11100101 A
b11100100 @
b10100110 ?
b10100101 >
b10100100 =
b1100110 <
b1100101 ;
b1100100 :
b100101 8
16
#1980
06
#1990
b11100111 B
b11100110 A
b11100101 @
b10100111 ?
b10100110 >
b10100101 =
b1100111 <
b1100110 ;
b1100101 :
b100110 8
16
#2000
06
#2010
b11101000 B
b11100111 A
b11100110 @
b10101000 ?
b10100111 >
b10100110 =
b1101000 <
b1100111 ;
b1100110 :
b100111 8
16
#2020
06
#2030
b11101001 B
b11101000 A
b11100111 @
b10101001 ?
b10101000 >
b10100111 =
b1101001 <
b1101000 ;
b1100111 :
b101000 8
16
#2040
06
#2050
b11101010 B
b11101001 A
b11101000 @
b10101010 ?
b10101001 >
b10101000 =
b1101010 <
b1101001 ;
b1101000 :
b101001 8
16
#2060
06
#2070
b11101011 B
b11101010 A
b11101001 @
b10101011 ?
b10101010 >
b10101001 =
b1101011 <
b1101010 ;
b1101001 :
b101010 8
16
#2080
06
#2090
b11101100 B
b11101011 A
b11101010 @
b10101100 ?
b10101011 >
b10101010 =
b1101100 <
b1101011 ;
b1101010 :
b101011 8
16
#2100
06
#2110
1!
b10100110 "
0/
b1100111 #
00
b11000001 *
b11000001 S
b10000010 )
b10000010 P
b11000001 $
b11000001 Q
1.
b10000010 &
b10000010 N
11
b0 F
b11000001 '
b11000001 R
b1111110 -
b111111 4
b10000010 %
b10000010 O
b111111 ,
b0 2
b0 E
b11101101 B
b11101100 A
b11101011 @
b10101101 ?
b10101100 >
b10101011 =
b1101101 <
b1101100 ;
b1101011 :
b101100 8
16
#2120
06
#2130
b11101110 B
b11101101 A
b11101100 @
b10101110 ?
b10101101 >
b10101100 =
b1101110 <
b1101101 ;
b1101100 :
b101101 8
16
#2140
06
#2150
b101000 #
b1000011 )
b1000011 P
b1000011 &
b1000011 N
b1111110 (
b111111 5
b1000011 %
b1000011 O
b0 ,
b0 I
b0 H
b11000001 '
b11000001 R
b111111 -
b0 4
b0 D
b11101111 B
b11101110 A
b11101101 @
b10101111 ?
b10101110 >
b10101101 =
b1101111 <
b1101110 ;
b1101101 :
b101110 8
16
#2160
06
#2170
b11110000 B
b11101111 A
b11101110 @
b10110000 ?
b10101111 >
b10101110 =
b1110000 <
b1101111 ;
b1101110 :
b101111 8
16
#2180
06
#2190
b10100110 #
b11100101 "
1/
b11000001 )
b11000001 P
b0 *
b0 S
0.
b11000001 &
b11000001 N
b0 $
b0 Q
b0 L
b0 (
b0 5
b0 K
b11000001 %
b11000001 O
b111111 +
b111111 3
b0 '
b0 R
b0 -
b0 G
b11110001 B
b11110000 A
b11101111 @
b10110001 ?
b10110000 >
b10101111 =
b1110001 <
b1110000 ;
b1101111 :
b110000 8
16
#2200
06
#2210
b11110010 B
b11110001 A
b11110000 @
b10110010 ?
b10110001 >
b10110000 =
b1110010 <
b1110001 ;
b1110000 :
b110001 8
16
#2220
06
