lab2/task2.v
module task2(x0,
             h0,
             h1,
             h2,
             clk,
             reset,
             y);
    input [3:0]x0 ,h0, h1, h2;
    input clk, reset;
    output [7:0]y;
    
    reg [3:0]x1, x2;
    wire [7:0] w0, w1, w2, w01;
    
    assign w0  = x0 * h0;
    assign w1  = x1 * h1;
    assign w2  = x2 * h2;
    assign w01 = w0 + w1;
    assign y   = w01 +w2;
    
    always@(posedge clk, negedge reset)
    begin
        if (reset == 0)
        begin
            x1 <= 0;
            x2 <= 0;
        end
        else
        begin
            x1 <= x0;
            x2 <= x1;
        end
    end
endmodule

lab2/task2_tb.v
`include "task2.v"
module task2_tb();
    reg [3:0]x0 ,h0, h1, h2;
    reg clk, reset;
    wire [7:0]y;
    
    task2 obj(x0, h0, h1, h2, clk, reset, y);
    initial
    begin
        $dumpfile("task2.vcd");
        $dumpvars(0, task2_tb);
        $display("done testing case %d", y);
        clk = 0; reset = 0; x0 = 0; h0 = 1; h1 = 2; h2 = 1;
        #10
        reset = 1;
        #10
        x0 = 1;
        #10
        x0 = 2;
        #10
        x0 = 3;
        #10
        x0 = 4;
        #10
        x0 = 5;
        $finish;
    end
    
    always
    begin
    #5
    clk = !clk;
    end
endmodule

lab2/task2.vcd
$date
	Tue Oct 15 06:36:17 2019
$end
$version
	Icarus Verilog
$end
$timescale
	1s
$end
$scope module task2_tb $end
$var wire 8 ! y [7:0] $end
$var reg 1 " clk $end
$var reg 4 # h0 [3:0] $end
$var reg 4 $ h1 [3:0] $end
$var reg 4 % h2 [3:0] $end
$var reg 1 & reset $end
$var reg 4 ' x0 [3:0] $end
$scope module obj $end
$var wire 1 " clk $end
$var wire 4 ( h0 [3:0] $end
$var wire 4 ) h1 [3:0] $end
$var wire 4 * h2 [3:0] $end
$var wire 1 & reset $end
$var wire 4 + x0 [3:0] $end
$var wire 8 , y [7:0] $end
$var wire 8 - w2 [7:0] $end
$var wire 8 . w1 [7:0] $end
$var wire 8 / w01 [7:0] $end
$var wire 8 0 w0 [7:0] $end
$var reg 4 1 x1 [3:0] $end
$var reg 4 2 x2 [3:0] $end
$upscope $end
$upscope $end
$enddefinitions $end
#0
$dumpvars
b0 2
b0 1
b0 0
b0 /
b0 .
b0 -
b0 ,
b0 +
b1 *
b10 )
b1 (
b0 '
0&
b1 %
b10 $
b1 #
0"
b0 !
$end
#5
1"
#10
0"
1&
#15
1"
#20
0"
b1 !
b1 ,
b1 /
b1 0
b1 '
b1 +
#25
b11 !
b11 ,
b11 /
b10 .
b1 1
1"
#30
0"
b100 !
b100 ,
b100 /
b10 0
b10 '
b10 +
#35
b1 -
b1 2
b111 !
b111 ,
b110 /
b100 .
b10 1
1"
#40
0"
b1000 !
b1000 ,
b111 /
b11 0
b11 '
b11 +
#45
b10 -
b10 2
b1011 !
b1011 ,
b1001 /
b110 .
b11 1
1"
#50
0"
b1100 !
b1100 ,
b1010 /
b100 0
b100 '
b100 +
#55
b11 -
b11 2
b1111 !
b1111 ,
b1100 /
b1000 .
b100 1
1"
#60
0"
b10000 !
b10000 ,
b1101 /
b101 0
b101 '
b101 +
